Workbook

Sheet G3 Multi 
A1: TIPO | B1: CODIGO | C1: PRODUCTO | D1: PRECIO $ Publicado | E1: PRECIO $ BCV Pub. | F1: PRECIO $ G3Multi | G1: PRECIO $ BCV | H1: PRECIO Bs. | I1: UTILIDAD | J1: P. VENTA UTIL. | K1: diff.
A2: {=Roccia!A2:C997} -> ARTÍCULOS DE COCINA | B2: K001 | C2: JUEGO DE OLLAS DE GRANITO ANTIADHERENTE 12 PIEZAS DE LUJO NERO ROCCIA | D2: =IF(MOD(F2, 5) <= 2.5, FLOOR(F2, 5), CEILING(F2, 5)) -> 145 | E2: =IF(MOD(G2, 5) <= 2.5, FLOOR(G2, 5), CEILING(G2, 5)) -> 215 | F2: =IFERROR((VLOOKUP(B2, Roccia!$B$2:$D997, 3, FALSE)*(1+Datos!$E$1)), "Revisar") -> 143.403 | G2: =IFERROR(F2*Datos!$B$3, "Revisar") -> 215.1045 | H2: =IFERROR(G2*Datos!$B$1, "Revisar") -> 124232.77 | I2: =IFERROR((VLOOKUP(B2, Roccia!$B$2:$D997, 3, FALSE) /(1-Datos!$E$1)), "Revisar") -> 157.58571 | J2: =IFERROR(I2*Datos!$B$3, "Revisar") -> 236.37857 | K2: =IFERROR(J2-G2, "Revisar") -> 21.274071
A3: ARTÍCULOS DE COCINA | B3: K003 | C3: JUEGO DE SARTENES 3 PIEZAS NERO MARCA ROCCIA | D3: =IF(MOD(F3, 5) <= 2.5, FLOOR(F3, 5), CEILING(F3, 5)) -> 45 | E3: =IF(MOD(G3, 5) <= 2.5, FLOOR(G3, 5), CEILING(G3, 5)) -> 70 | F3: =IFERROR((VLOOKUP(B3, Roccia!$B$2:$D997, 3, FALSE)*(1+Datos!$E$1)), "Revisar") -> 46.982 | G3: =IFERROR(F3*Datos!$B$3, "Revisar") -> 70.473 | H3: =IFERROR(G3*Datos!$B$1, "Revisar") -> 40701.406 | I3: =IFERROR((VLOOKUP(B3, Roccia!$B$2:$D997, 3, FALSE) /(1-Datos!$E$1)), "Revisar") -> 51.628571 | J3: =IFERROR(I3*Datos!$B$3, "Revisar") -> 77.442857 | K3: =IFERROR(J3-G3, "Revisar") -> 6.9698571
A4: ARTÍCULOS DE COCINA | B4: K004 | C4: WOK DE 28CM CON TAPA DE CRISTAL MARCA ROCCIA | D4: =IF(MOD(F4, 5) <= 2.5, FLOOR(F4, 5), CEILING(F4, 5)) -> 30 | E4: =IF(MOD(G4, 5) <= 2.5, FLOOR(G4, 5), CEILING(G4, 5)) -> 40 | F4: =IFERROR((VLOOKUP(B4, Roccia!$B$2:$D997, 3, FALSE)*(1+Datos!$E$1)), "Revisar") -> 28.041 | G4: =IFERROR(F4*Datos!$B$3, "Revisar") -> 42.0615 | H4: =IFERROR(G4*Datos!$B$1, "Revisar") -> 24292.455 | I4: =IFERROR((VLOOKUP(B4, Roccia!$B$2:$D997, 3, FALSE) /(1-Datos!$E$1)), "Revisar") -> 30.814286 | J4: =IFERROR(I4*Datos!$B$3, "Revisar") -> 46.221429 | K4: =IFERROR(J4-G4, "Revisar") -> 4.1599286
A5: ARTÍCULOS DE COCINA | B5: K005 | C5: JUEGO DE OLLAS GRANITE 14 PIEZAS MARCA ROCCIA | D5: =IF(MOD(F5, 5) <= 2.5, FLOOR(F5, 5), CEILING(F5, 5)) -> 115 | E5: =IF(MOD(G5, 5) <= 2.5, FLOOR(G5, 5), CEILING(G5, 5)) -> 170 | F5: =IFERROR((VLOOKUP(B5, Roccia!$B$2:$D997, 3, FALSE)*(1+Datos!$E$1)), "Revisar") -> 113.815 | G5: =IFERROR(F5*Datos!$B$3, "Revisar") -> 170.7225 | H5: =IFERROR(G5*Datos!$B$1, "Revisar") -> 98600.114 | I5: =IFERROR((VLOOKUP(B5, Roccia!$B$2:$D997, 3, FALSE) /(1-Datos!$E$1)), "Revisar") -> 125.07143 | J5: =IFERROR(I5*Datos!$B$3, "Revisar") -> 187.60714 | K5: =IFERROR(J5-G5, "Revisar") -> 16.884643
A6: ARTÍCULOS DE COCINA | B6: K006 | C6: BUDARE 28CM CUADRADO NERO MARCA ROCCIA | D6: =IF(MOD(F6, 5) <= 2.5, FLOOR(F6, 5), CEILING(F6, 5)) -> 15 | E6: =IF(MOD(G6, 5) <= 2.5, FLOOR(G6, 5), CEILING(G6, 5)) -> 20 | F6: =IFERROR((VLOOKUP(B6, Roccia!$B$2:$D997, 3, FALSE)*(1+Datos!$E$1)), "Revisar") -> 14.287 | G6: =IFERROR(F6*Datos!$B$3, "Revisar") -> 21.4305 | H6: =IFERROR(G6*Datos!$B$1, "Revisar") -> 12377.102 | I6: =IFERROR((VLOOKUP(B6, Roccia!$B$2:$D997, 3, FALSE) /(1-Datos!$E$1)), "Revisar") -> 15.7 | J6: =IFERROR(I6*Datos!$B$3, "Revisar") -> 23.55 | K6: =IFERROR(J6-G6, "Revisar") -> 2.1195
A7: ARTÍCULOS DE COCINA | B7: K007G | C7: JUEGO DE UTENSILIOS DE COCINA 12 PIEZAS SILICONE ANTIRAYA GRIS | D7: =IF(MOD(F7, 5) <= 2.5, FLOOR(F7, 5), CEILING(F7, 5)) -> 15 | E7: =IF(MOD(G7, 5) <= 2.5, FLOOR(G7, 5), CEILING(G7, 5)) -> 20 | F7: =IFERROR((VLOOKUP(B7, Roccia!$B$2:$D997, 3, FALSE)*(1+Datos!$E$1)), "Revisar") -> 14.3 | G7: =IFERROR(F7*Datos!$B$3, "Revisar") -> 21.45 | H7: =IFERROR(G7*Datos!$B$1, "Revisar") -> 12388.364 | I7: =IFERROR((VLOOKUP(B7, Roccia!$B$2:$D997, 3, FALSE) /(1-Datos!$E$1)), "Revisar") -> 15.714286 | J7: =IFERROR(I7*Datos!$B$3, "Revisar") -> 23.571429 | K7: =IFERROR(J7-G7, "Revisar") -> 2.1214286
A8: ARTÍCULOS DE COCINA | B8: K007V | C8: JUEGO DE UTENSILIOS DE COCINA 12 PIEZAS SILICONE ANTIRAYA VERDE | D8: =IF(MOD(F8, 5) <= 2.5, FLOOR(F8, 5), CEILING(F8, 5)) -> 15 | E8: =IF(MOD(G8, 5) <= 2.5, FLOOR(G8, 5), CEILING(G8, 5)) -> 20 | F8: =IFERROR((VLOOKUP(B8, Roccia!$B$2:$D997, 3, FALSE)*(1+Datos!$E$1)), "Revisar") -> 14.3 | G8: =IFERROR(F8*Datos!$B$3, "Revisar") -> 21.45 | H8: =IFERROR(G8*Datos!$B$1, "Revisar") -> 12388.364 | I8: =IFERROR((VLOOKUP(B8, Roccia!$B$2:$D997, 3, FALSE) /(1-Datos!$E$1)), "Revisar") -> 15.714286 | J8: =IFERROR(I8*Datos!$B$3, "Revisar") -> 23.571429 | K8: =IFERROR(J8-G8, "Revisar") -> 2.1214286
A9: ARTÍCULOS DE COCINA | B9: K007N | C9: JUEGO DE UTENSILIOS DE COCINA 12 PIEZAS SILICONE ANTIRAYA NEGRO | D9: =IF(MOD(F9, 5) <= 2.5, FLOOR(F9, 5), CEILING(F9, 5)) -> 15 | E9: =IF(MOD(G9, 5) <= 2.5, FLOOR(G9, 5), CEILING(G9, 5)) -> 20 | F9: =IFERROR((VLOOKUP(B9, Roccia!$B$2:$D997, 3, FALSE)*(1+Datos!$E$1)), "Revisar") -> 14.3 | G9: =IFERROR(F9*Datos!$B$3, "Revisar") -> 21.45 | H9: =IFERROR(G9*Datos!$B$1, "Revisar") -> 12388.364 | I9: =IFERROR((VLOOKUP(B9, Roccia!$B$2:$D997, 3, FALSE) /(1-Datos!$E$1)), "Revisar") -> 15.714286 | J9: =IFERROR(I9*Datos!$B$3, "Revisar") -> 23.571429 | K9: =IFERROR(J9-G9, "Revisar") -> 2.1214286
A10: ARTÍCULOS DE COCINA | B10: K007B | C10: JUEGO DE UTENSILIOS DE COCINA 12 PIEZAS SILICONE ANTIRAYA BEIGE | D10: =IF(MOD(F10, 5) <= 2.5, FLOOR(F10, 5), CEILING(F10, 5)) -> 15 | E10: =IF(MOD(G10, 5) <= 2.5, FLOOR(G10, 5), CEILING(G10, 5)) -> 20 | F10: =IFERROR((VLOOKUP(B10, Roccia!$B$2:$D997, 3, FALSE)*(1+Datos!$E$1)), "Revisar") -> 14.3 | G10: =IFERROR(F10*Datos!$B$3, "Revisar") -> 21.45 | H10: =IFERROR(G10*Datos!$B$1, "Revisar") -> 12388.364 | I10: =IFERROR((VLOOKUP(B10, Roccia!$B$2:$D997, 3, FALSE) /(1-Datos!$E$1)), "Revisar") -> 15.714286 | J10: =IFERROR(I10*Datos!$B$3, "Revisar") -> 23.571429 | K10: =IFERROR(J10-G10, "Revisar") -> 2.1214286
A11: ARTÍCULOS DE COCINA | B11: K008 | C11: JUEGO DE 7 CUCHILLOS DE ALTA GAMA MARCA ROCCIA | D11: =IF(MOD(F11, 5) <= 2.5, FLOOR(F11, 5), CEILING(F11, 5)) -> 40 | E11: =IF(MOD(G11, 5) <= 2.5, FLOOR(G11, 5), CEILING(G11, 5)) -> 60 | F11: =IFERROR((VLOOKUP(B11, Roccia!$B$2:$D997, 3, FALSE)*(1+Datos!$E$1)), "Revisar") -> 40.183 | G11: =IFERROR(F11*Datos!$B$3, "Revisar") -> 60.2745 | H11: =IFERROR(G11*Datos!$B$1, "Revisar") -> 34811.302 | I11: =IFERROR((VLOOKUP(B11, Roccia!$B$2:$D997, 3, FALSE) /(1-Datos!$E$1)), "Revisar") -> 44.157143 | J11: =IFERROR(I11*Datos!$B$3, "Revisar") -> 66.235714 | K11: =IFERROR(J11-G11, "Revisar") -> 5.9612143
A12: ARTÍCULOS DE COCINA | B12: K009 | C12: JUEGO DE 5 CUCHILLOS DE ACERO INOXIDABLE | D12: =IF(MOD(F12, 5) <= 2.5, FLOOR(F12, 5), CEILING(F12, 5)) -> 20 | E12: =IF(MOD(G12, 5) <= 2.5, FLOOR(G12, 5), CEILING(G12, 5)) -> 30 | F12: =IFERROR((VLOOKUP(B12, Roccia!$B$2:$D997, 3, FALSE)*(1+Datos!$E$1)), "Revisar") -> 19.5 | G12: =IFERROR(F12*Datos!$B$3, "Revisar") -> 29.25 | H12: =IFERROR(G12*Datos!$B$1, "Revisar") -> 16893.223 | I12: =IFERROR((VLOOKUP(B12, Roccia!$B$2:$D997, 3, FALSE) /(1-Datos!$E$1)), "Revisar") -> 21.428571 | J12: =IFERROR(I12*Datos!$B$3, "Revisar") -> 32.142857 | K12: =IFERROR(J12-G12, "Revisar") -> 2.8928571
A13: ARTÍCULOS DE COCINA | B13: K010 | C13: SET DE OLLAS DILUSSO 8 PIEZAS DE ACERO INOXIDABLE MARCA ROCCIA | D13: =IF(MOD(F13, 5) <= 2.5, FLOOR(F13, 5), CEILING(F13, 5)) -> 130 | E13: =IF(MOD(G13, 5) <= 2.5, FLOOR(G13, 5), CEILING(G13, 5)) -> 195 | F13: =IFERROR((VLOOKUP(B13, Roccia!$B$2:$D997, 3, FALSE)*(1+Datos!$E$1)), "Revisar") -> 131.001 | G13: =IFERROR(F13*Datos!$B$3, "Revisar") -> 196.5015 | H13: =IFERROR(G13*Datos!$B$1, "Revisar") -> 113488.68 | I13: =IFERROR((VLOOKUP(B13, Roccia!$B$2:$D997, 3, FALSE) /(1-Datos!$E$1)), "Revisar") -> 143.95714 | J13: =IFERROR(I13*Datos!$B$3, "Revisar") -> 215.93571 | K13: =IFERROR(J13-G13, "Revisar") -> 19.434214
A14: ARTÍCULOS DE COCINA | B14: K011 | C14: JUEGO DE OLLAS GRANITE GRIS 14 PIEZAS EURO-14SET MARCA ROCCIA | D14: =IF(MOD(F14, 5) <= 2.5, FLOOR(F14, 5), CEILING(F14, 5)) -> 120 | E14: =IF(MOD(G14, 5) <= 2.5, FLOOR(G14, 5), CEILING(G14, 5)) -> 175 | F14: =IFERROR((VLOOKUP(B14, Roccia!$B$2:$D997, 3, FALSE)*(1+Datos!$E$1)), "Revisar") -> 117.741 | G14: =IFERROR(F14*Datos!$B$3, "Revisar") -> 176.6115 | H14: =IFERROR(G14*Datos!$B$1, "Revisar") -> 102001.28 | I14: =IFERROR((VLOOKUP(B14, Roccia!$B$2:$D997, 3, FALSE) /(1-Datos!$E$1)), "Revisar") -> 129.38571 | J14: =IFERROR(I14*Datos!$B$3, "Revisar") -> 194.07857 | K14: =IFERROR(J14-G14, "Revisar") -> 17.467071
A15: ARTÍCULOS DE COCINA | B15: K012 | C15: JUEGO DE OLLAS Di'ROCCA NEGRO 10 PIEZAS ALTA GAMA OF25-10PCS | D15: =IF(MOD(F15, 5) <= 2.5, FLOOR(F15, 5), CEILING(F15, 5)) -> 120 | E15: =IF(MOD(G15, 5) <= 2.5, FLOOR(G15, 5), CEILING(G15, 5)) -> 180 | F15: =IFERROR((VLOOKUP(B15, Roccia!$B$2:$D997, 3, FALSE)*(1+Datos!$E$1)), "Revisar") -> 119.08 | G15: =IFERROR(F15*Datos!$B$3, "Revisar") -> 178.62 | H15: =IFERROR(G15*Datos!$B$1, "Revisar") -> 103161.28 | I15: =IFERROR((VLOOKUP(B15, Roccia!$B$2:$D997, 3, FALSE) /(1-Datos!$E$1)), "Revisar") -> 130.85714 | J15: =IFERROR(I15*Datos!$B$3, "Revisar") -> 196.28571 | K15: =IFERROR(J15-G15, "Revisar") -> 17.665714
A16: ARTÍCULOS DE COCINA | B16: K013 | C16: JUEGO DE OLLAS Di'ROCCA BLANCO 10 PIEZAS ALTA GAMA OF26-10PCS | D16: =IF(MOD(F16, 5) <= 2.5, FLOOR(F16, 5), CEILING(F16, 5)) -> 120 | E16: =IF(MOD(G16, 5) <= 2.5, FLOOR(G16, 5), CEILING(G16, 5)) -> 180 | F16: =IFERROR((VLOOKUP(B16, Roccia!$B$2:$D997, 3, FALSE)*(1+Datos!$E$1)), "Revisar") -> 119.08 | G16: =IFERROR(F16*Datos!$B$3, "Revisar") -> 178.62 | H16: =IFERROR(G16*Datos!$B$1, "Revisar") -> 103161.28 | I16: =IFERROR((VLOOKUP(B16, Roccia!$B$2:$D997, 3, FALSE) /(1-Datos!$E$1)), "Revisar") -> 130.85714 | J16: =IFERROR(I16*Datos!$B$3, "Revisar") -> 196.28571 | K16: =IFERROR(J16-G16, "Revisar") -> 17.665714
A17: ARTICULOS PARA PISCINAS | B17: B029L | C17: LAMPARA LED PARA PISCINA 29.2*7CM CON BORDE 12W/12V YC292-A | D17: =IF(MOD(F17, 5) <= 2.5, FLOOR(F17, 5), CEILING(F17, 5)) -> 55 | E17: =IF(MOD(G17, 5) <= 2.5, FLOOR(G17, 5), CEILING(G17, 5)) -> 80 | F17: =IFERROR((VLOOKUP(B17, Roccia!$B$2:$D997, 3, FALSE)*(1+Datos!$E$1)), "Revisar") -> 52.663 | G17: =IFERROR(F17*Datos!$B$3, "Revisar") -> 78.9945 | H17: =IFERROR(G17*Datos!$B$1, "Revisar") -> 45622.965 | I17: =IFERROR((VLOOKUP(B17, Roccia!$B$2:$D997, 3, FALSE) /(1-Datos!$E$1)), "Revisar") -> 57.871429 | J17: =IFERROR(I17*Datos!$B$3, "Revisar") -> 86.807143 | K17: =IFERROR(J17-G17, "Revisar") -> 7.8126429
A18: ARTICULOS PARA PISCINAS | B18: B030L | C18: LAMPARA LED PARA PISCINA 29.5*7CM BORDE INFINITO 12W/12V YC295-2A | D18: =IF(MOD(F18, 5) <= 2.5, FLOOR(F18, 5), CEILING(F18, 5)) -> 55 | E18: =IF(MOD(G18, 5) <= 2.5, FLOOR(G18, 5), CEILING(G18, 5)) -> 85 | F18: =IFERROR((VLOOKUP(B18, Roccia!$B$2:$D997, 3, FALSE)*(1+Datos!$E$1)), "Revisar") -> 56.771 | G18: =IFERROR(F18*Datos!$B$3, "Revisar") -> 85.1565 | H18: =IFERROR(G18*Datos!$B$1, "Revisar") -> 49181.804 | I18: =IFERROR((VLOOKUP(B18, Roccia!$B$2:$D997, 3, FALSE) /(1-Datos!$E$1)), "Revisar") -> 62.385714 | J18: =IFERROR(I18*Datos!$B$3, "Revisar") -> 93.578571 | K18: =IFERROR(J18-G18, "Revisar") -> 8.4220714
A19: ARTICULOS PARA PISCINAS | B19: B031L | C19: LAMPARA LED PARA PISCINA 23*4.8CM 12W/12V YC230-2A | D19: =IF(MOD(F19, 5) <= 2.5, FLOOR(F19, 5), CEILING(F19, 5)) -> 55 | E19: =IF(MOD(G19, 5) <= 2.5, FLOOR(G19, 5), CEILING(G19, 5)) -> 80 | F19: =IFERROR((VLOOKUP(B19, Roccia!$B$2:$D997, 3, FALSE)*(1+Datos!$E$1)), "Revisar") -> 52.624 | G19: =IFERROR(F19*Datos!$B$3, "Revisar") -> 78.936 | H19: =IFERROR(G19*Datos!$B$1, "Revisar") -> 45589.179 | I19: =IFERROR((VLOOKUP(B19, Roccia!$B$2:$D997, 3, FALSE) /(1-Datos!$E$1)), "Revisar") -> 57.828571 | J19: =IFERROR(I19*Datos!$B$3, "Revisar") -> 86.742857 | K19: =IFERROR(J19-G19, "Revisar") -> 7.8068571
A20: ARTICULOS PARA PISCINAS | B20: B032L | C20: LAMPARA LED PARA PISCINA 23*4.8CM 12W/12V YC230-SW | D20: =IF(MOD(F20, 5) <= 2.5, FLOOR(F20, 5), CEILING(F20, 5)) -> 55 | E20: =IF(MOD(G20, 5) <= 2.5, FLOOR(G20, 5), CEILING(G20, 5)) -> 80 | F20: =IFERROR((VLOOKUP(B20, Roccia!$B$2:$D997, 3, FALSE)*(1+Datos!$E$1)), "Revisar") -> 52.663 | G20: =IFERROR(F20*Datos!$B$3, "Revisar") -> 78.9945 | H20: =IFERROR(G20*Datos!$B$1, "Revisar") -> 45622.965 | I20: =IFERROR((VLOOKUP(B20, Roccia!$B$2:$D997, 3, FALSE) /(1-Datos!$E$1)), "Revisar") -> 57.871429 | J20: =IFERROR(I20*Datos!$B$3, "Revisar") -> 86.807143 | K20: =IFERROR(J20-G20, "Revisar") -> 7.8126429
A21: ARTICULOS PARA PISCINAS | B21: B033L | C21: LAMPARA LED PARA PISCINA 30*7CM 18W/12V YC300-SW | D21: =IF(MOD(F21, 5) <= 2.5, FLOOR(F21, 5), CEILING(F21, 5)) -> 75 | E21: =IF(MOD(G21, 5) <= 2.5, FLOOR(G21, 5), CEILING(G21, 5)) -> 115 | F21: =IFERROR((VLOOKUP(B21, Roccia!$B$2:$D997, 3, FALSE)*(1+Datos!$E$1)), "Revisar") -> 76.076 | G21: =IFERROR(F21*Datos!$B$3, "Revisar") -> 114.114 | H21: =IFERROR(G21*Datos!$B$1, "Revisar") -> 65906.096 | I21: =IFERROR((VLOOKUP(B21, Roccia!$B$2:$D997, 3, FALSE) /(1-Datos!$E$1)), "Revisar") -> 83.6 | J21: =IFERROR(I21*Datos!$B$3, "Revisar") -> 125.4 | K21: =IFERROR(J21-G21, "Revisar") -> 11.286
A22: ARTICULOS PARA PISCINAS | B22: B034L | C22: ASPIRADORA DE PISCINAS RECARGABLE 2000MAH 40W RPC403 MARCA ROCCIA | D22: =IF(MOD(F22, 5) <= 2.5, FLOOR(F22, 5), CEILING(F22, 5)) -> 115 | E22: =IF(MOD(G22, 5) <= 2.5, FLOOR(G22, 5), CEILING(G22, 5)) -> 175 | F22: =IFERROR((VLOOKUP(B22, Roccia!$B$2:$D997, 3, FALSE)*(1+Datos!$E$1)), "Revisar") -> 116.415 | G22: =IFERROR(F22*Datos!$B$3, "Revisar") -> 174.6225 | H22: =IFERROR(G22*Datos!$B$1, "Revisar") -> 100852.54 | I22: =IFERROR((VLOOKUP(B22, Roccia!$B$2:$D997, 3, FALSE) /(1-Datos!$E$1)), "Revisar") -> 127.92857 | J22: =IFERROR(I22*Datos!$B$3, "Revisar") -> 191.89286 | K22: =IFERROR(J22-G22, "Revisar") -> 17.270357
A23: ARTICULOS PARA PISCINAS | B23: B035L | C23: CLORIFICADOR SALINO INTELIGENTE 25g/h PARA PISCINAS LC250A | D23: =IF(MOD(F23, 5) <= 2.5, FLOOR(F23, 5), CEILING(F23, 5)) -> 505 | E23: =IF(MOD(G23, 5) <= 2.5, FLOOR(G23, 5), CEILING(G23, 5)) -> 755 | F23: =IFERROR((VLOOKUP(B23, Roccia!$B$2:$D997, 3, FALSE)*(1+Datos!$E$1)), "Revisar") -> 502.84 | G23: =IFERROR(F23*Datos!$B$3, "Revisar") -> 754.26 | H23: =IFERROR(G23*Datos!$B$1, "Revisar") -> 435619.92 | I23: =IFERROR((VLOOKUP(B23, Roccia!$B$2:$D997, 3, FALSE) /(1-Datos!$E$1)), "Revisar") -> 552.57143 | J23: =IFERROR(I23*Datos!$B$3, "Revisar") -> 828.85714 | K23: =IFERROR(J23-G23, "Revisar") -> 74.597143
A24: ARTICULOS PARA PISCINAS | B24: B036L | C24: CLORIFICADOR SALINO INTELIGENTE 30g/h PARA PISCINAS LC300A | D24: =IF(MOD(F24, 5) <= 2.5, FLOOR(F24, 5), CEILING(F24, 5)) -> 570 | E24: =IF(MOD(G24, 5) <= 2.5, FLOOR(G24, 5), CEILING(G24, 5)) -> 855 | F24: =IFERROR((VLOOKUP(B24, Roccia!$B$2:$D997, 3, FALSE)*(1+Datos!$E$1)), "Revisar") -> 569.179 | G24: =IFERROR(F24*Datos!$B$3, "Revisar") -> 853.7685 | H24: =IFERROR(G24*Datos!$B$1, "Revisar") -> 493090.67 | I24: =IFERROR((VLOOKUP(B24, Roccia!$B$2:$D997, 3, FALSE) /(1-Datos!$E$1)), "Revisar") -> 625.47143 | J24: =IFERROR(I24*Datos!$B$3, "Revisar") -> 938.20714 | K24: =IFERROR(J24-G24, "Revisar") -> 84.438643
A25: ARTICULOS PARA PISCINAS | B25: B037L | C25: CLORIFICADOR SALINO INTELIGENTE 40g/h PARA PISCINAS LC400A | D25: =IF(MOD(F25, 5) <= 2.5, FLOOR(F25, 5), CEILING(F25, 5)) -> 725 | E25: =IF(MOD(G25, 5) <= 2.5, FLOOR(G25, 5), CEILING(G25, 5)) -> 1090 | F25: =IFERROR((VLOOKUP(B25, Roccia!$B$2:$D997, 3, FALSE)*(1+Datos!$E$1)), "Revisar") -> 727.363 | G25: =IFERROR(F25*Datos!$B$3, "Revisar") -> 1091.0445 | H25: =IFERROR(G25*Datos!$B$1, "Revisar") -> 630128.5 | I25: =IFERROR((VLOOKUP(B25, Roccia!$B$2:$D997, 3, FALSE) /(1-Datos!$E$1)), "Revisar") -> 799.3 | J25: =IFERROR(I25*Datos!$B$3, "Revisar") -> 1198.95 | K25: =IFERROR(J25-G25, "Revisar") -> 107.9055
A26: ARTICULOS PARA PISCINAS | B26: B038L | C26: CLORIFICADOR SALINO INTELIGENTE 50g/h PARA PISCINAS LC500A | D26: =IF(MOD(F26, 5) <= 2.5, FLOOR(F26, 5), CEILING(F26, 5)) -> 885 | E26: =IF(MOD(G26, 5) <= 2.5, FLOOR(G26, 5), CEILING(G26, 5)) -> 1325 | F26: =IFERROR((VLOOKUP(B26, Roccia!$B$2:$D997, 3, FALSE)*(1+Datos!$E$1)), "Revisar") -> 883.012 | G26: =IFERROR(F26*Datos!$B$3, "Revisar") -> 1324.518 | H26: =IFERROR(G26*Datos!$B$1, "Revisar") -> 764970.21 | I26: =IFERROR((VLOOKUP(B26, Roccia!$B$2:$D997, 3, FALSE) /(1-Datos!$E$1)), "Revisar") -> 970.34286 | J26: =IFERROR(I26*Datos!$B$3, "Revisar") -> 1455.5143 | K26: =IFERROR(J26-G26, "Revisar") -> 130.99629
A27: BALANZAS | B27: P001 | C27: BALANZA DE 40 KG | D27: =IF(MOD(F27, 5) <= 2.5, FLOOR(F27, 5), CEILING(F27, 5)) -> 35 | E27: =IF(MOD(G27, 5) <= 2.5, FLOOR(G27, 5), CEILING(G27, 5)) -> 50 | F27: =IFERROR((VLOOKUP(B27, Roccia!$B$2:$D997, 3, FALSE)*(1+Datos!$E$1)), "Revisar") -> 33.8 | G27: =IFERROR(F27*Datos!$B$3, "Revisar") -> 50.7 | H27: =IFERROR(G27*Datos!$B$1, "Revisar") -> 29281.587 | I27: =IFERROR((VLOOKUP(B27, Roccia!$B$2:$D997, 3, FALSE) /(1-Datos!$E$1)), "Revisar") -> 37.142857 | J27: =IFERROR(I27*Datos!$B$3, "Revisar") -> 55.714286 | K27: =IFERROR(J27-G27, "Revisar") -> 5.0142857
A28: BALANZAS | B28: P003 | C28: BALANZA DE 7 KG | D28: =IF(MOD(F28, 5) <= 2.5, FLOOR(F28, 5), CEILING(F28, 5)) -> 5 | E28: =IF(MOD(G28, 5) <= 2.5, FLOOR(G28, 5), CEILING(G28, 5)) -> 5 | F28: =IFERROR((VLOOKUP(B28, Roccia!$B$2:$D997, 3, FALSE)*(1+Datos!$E$1)), "Revisar") -> 4.55 | G28: =IFERROR(F28*Datos!$B$3, "Revisar") -> 6.825 | H28: =IFERROR(G28*Datos!$B$1, "Revisar") -> 3941.7521 | I28: =IFERROR((VLOOKUP(B28, Roccia!$B$2:$D997, 3, FALSE) /(1-Datos!$E$1)), "Revisar") -> 5 | J28: =IFERROR(I28*Datos!$B$3, "Revisar") -> 7.5 | K28: =IFERROR(J28-G28, "Revisar") -> 0.675
A29: BALANZAS | B29: P011 | C29: ROMANA DE 200 KG | D29: =IF(MOD(F29, 5) <= 2.5, FLOOR(F29, 5), CEILING(F29, 5)) -> 55 | E29: =IF(MOD(G29, 5) <= 2.5, FLOOR(G29, 5), CEILING(G29, 5)) -> 80 | F29: =IFERROR((VLOOKUP(B29, Roccia!$B$2:$D997, 3, FALSE)*(1+Datos!$E$1)), "Revisar") -> 54.6 | G29: =IFERROR(F29*Datos!$B$3, "Revisar") -> 81.9 | H29: =IFERROR(G29*Datos!$B$1, "Revisar") -> 47301.026 | I29: =IFERROR((VLOOKUP(B29, Roccia!$B$2:$D997, 3, FALSE) /(1-Datos!$E$1)), "Revisar") -> 60 | J29: =IFERROR(I29*Datos!$B$3, "Revisar") -> 90 | K29: =IFERROR(J29-G29, "Revisar") -> 8.1
A30: BALANZAS | B30: P012 | C30: ROMANA DE 350 KG | D30: =IF(MOD(F30, 5) <= 2.5, FLOOR(F30, 5), CEILING(F30, 5)) -> 80 | E30: =IF(MOD(G30, 5) <= 2.5, FLOOR(G30, 5), CEILING(G30, 5)) -> 115 | F30: =IFERROR((VLOOKUP(B30, Roccia!$B$2:$D997, 3, FALSE)*(1+Datos!$E$1)), "Revisar") -> 78 | G30: =IFERROR(F30*Datos!$B$3, "Revisar") -> 117 | H30: =IFERROR(G30*Datos!$B$1, "Revisar") -> 67572.894 | I30: =IFERROR((VLOOKUP(B30, Roccia!$B$2:$D997, 3, FALSE) /(1-Datos!$E$1)), "Revisar") -> 85.714286 | J30: =IFERROR(I30*Datos!$B$3, "Revisar") -> 128.57143 | K30: =IFERROR(J30-G30, "Revisar") -> 11.571429
A31: BALANZAS | B31: P013 | C31: ROMANA DE 700 KG | D31: =IF(MOD(F31, 5) <= 2.5, FLOOR(F31, 5), CEILING(F31, 5)) -> 130 | E31: =IF(MOD(G31, 5) <= 2.5, FLOOR(G31, 5), CEILING(G31, 5)) -> 195 | F31: =IFERROR((VLOOKUP(B31, Roccia!$B$2:$D997, 3, FALSE)*(1+Datos!$E$1)), "Revisar") -> 130 | G31: =IFERROR(F31*Datos!$B$3, "Revisar") -> 195 | H31: =IFERROR(G31*Datos!$B$1, "Revisar") -> 112621.49 | I31: =IFERROR((VLOOKUP(B31, Roccia!$B$2:$D997, 3, FALSE) /(1-Datos!$E$1)), "Revisar") -> 142.85714 | J31: =IFERROR(I31*Datos!$B$3, "Revisar") -> 214.28571 | K31: =IFERROR(J31-G31, "Revisar") -> 19.285714
A32: BALANZAS | B32: P014 | C32: ROMANA WIFI 300 KG | D32: =IF(MOD(F32, 5) <= 2.5, FLOOR(F32, 5), CEILING(F32, 5)) -> 95 | E32: =IF(MOD(G32, 5) <= 2.5, FLOOR(G32, 5), CEILING(G32, 5)) -> 145 | F32: =IFERROR((VLOOKUP(B32, Roccia!$B$2:$D997, 3, FALSE)*(1+Datos!$E$1)), "Revisar") -> 95.095 | G32: =IFERROR(F32*Datos!$B$3, "Revisar") -> 142.6425 | H32: =IFERROR(G32*Datos!$B$1, "Revisar") -> 82382.62 | I32: =IFERROR((VLOOKUP(B32, Roccia!$B$2:$D997, 3, FALSE) /(1-Datos!$E$1)), "Revisar") -> 104.5 | J32: =IFERROR(I32*Datos!$B$3, "Revisar") -> 156.75 | K32: =IFERROR(J32-G32, "Revisar") -> 14.1075
A33: BALANZAS | B33: P016 | C33: ROMANA DE 3T 1*1 | D33: =IF(MOD(F33, 5) <= 2.5, FLOOR(F33, 5), CEILING(F33, 5)) -> 485 | E33: =IF(MOD(G33, 5) <= 2.5, FLOOR(G33, 5), CEILING(G33, 5)) -> 730 | F33: =IFERROR((VLOOKUP(B33, Roccia!$B$2:$D997, 3, FALSE)*(1+Datos!$E$1)), "Revisar") -> 485.849 | G33: =IFERROR(F33*Datos!$B$3, "Revisar") -> 728.7735 | H33: =IFERROR(G33*Datos!$B$1, "Revisar") -> 420900.29 | I33: =IFERROR((VLOOKUP(B33, Roccia!$B$2:$D997, 3, FALSE) /(1-Datos!$E$1)), "Revisar") -> 533.9 | J33: =IFERROR(I33*Datos!$B$3, "Revisar") -> 800.85 | K33: =IFERROR(J33-G33, "Revisar") -> 72.0765
A34: BALANZAS | B34: P017 | C34: ROMANA DE 3T 1,20*1,20 | D34: =IF(MOD(F34, 5) <= 2.5, FLOOR(F34, 5), CEILING(F34, 5)) -> 515 | E34: =IF(MOD(G34, 5) <= 2.5, FLOOR(G34, 5), CEILING(G34, 5)) -> 775 | F34: =IFERROR((VLOOKUP(B34, Roccia!$B$2:$D997, 3, FALSE)*(1+Datos!$E$1)), "Revisar") -> 515.489 | G34: =IFERROR(F34*Datos!$B$3, "Revisar") -> 773.2335 | H34: =IFERROR(G34*Datos!$B$1, "Revisar") -> 446577.99 | I34: =IFERROR((VLOOKUP(B34, Roccia!$B$2:$D997, 3, FALSE) /(1-Datos!$E$1)), "Revisar") -> 566.47143 | J34: =IFERROR(I34*Datos!$B$3, "Revisar") -> 849.70714 | K34: =IFERROR(J34-G34, "Revisar") -> 76.473643
A35: BALANZAS | B35: P018 | C35: ROMANA DE 3T 1,50*2 | D35: =IF(MOD(F35, 5) <= 2.5, FLOOR(F35, 5), CEILING(F35, 5)) -> 850 | E35: =IF(MOD(G35, 5) <= 2.5, FLOOR(G35, 5), CEILING(G35, 5)) -> 1275 | F35: =IFERROR((VLOOKUP(B35, Roccia!$B$2:$D997, 3, FALSE)*(1+Datos!$E$1)), "Revisar") -> 848.926 | G35: =IFERROR(F35*Datos!$B$3, "Revisar") -> 1273.389 | H35: =IFERROR(G35*Datos!$B$1, "Revisar") -> 735440.85 | I35: =IFERROR((VLOOKUP(B35, Roccia!$B$2:$D997, 3, FALSE) /(1-Datos!$E$1)), "Revisar") -> 932.88571 | J35: =IFERROR(I35*Datos!$B$3, "Revisar") -> 1399.3286 | K35: =IFERROR(J35-G35, "Revisar") -> 125.93957
A36: BALANZAS | B36: P019 | C36: BALANZA DE GANCHO RECARGABLE 50KG GOOD QUALITY YZ-S03 | D36: =IF(MOD(F36, 5) <= 2.5, FLOOR(F36, 5), CEILING(F36, 5)) -> 10 | E36: =IF(MOD(G36, 5) <= 2.5, FLOOR(G36, 5), CEILING(G36, 5)) -> 15 | F36: =IFERROR((VLOOKUP(B36, Roccia!$B$2:$D997, 3, FALSE)*(1+Datos!$E$1)), "Revisar") -> 9.1 | G36: =IFERROR(F36*Datos!$B$3, "Revisar") -> 13.65 | H36: =IFERROR(G36*Datos!$B$1, "Revisar") -> 7883.5043 | I36: =IFERROR((VLOOKUP(B36, Roccia!$B$2:$D997, 3, FALSE) /(1-Datos!$E$1)), "Revisar") -> 10 | J36: =IFERROR(I36*Datos!$B$3, "Revisar") -> 15 | K36: =IFERROR(J36-G36, "Revisar") -> 1.35
A37: BALANZAS | B37: P020 | C37: BALANZA DE COCINA 3KG GOOD QUALITY X1-C3B | D37: =IF(MOD(F37, 5) <= 2.5, FLOOR(F37, 5), CEILING(F37, 5)) -> 20 | E37: =IF(MOD(G37, 5) <= 2.5, FLOOR(G37, 5), CEILING(G37, 5)) -> 30 | F37: =IFERROR((VLOOKUP(B37, Roccia!$B$2:$D997, 3, FALSE)*(1+Datos!$E$1)), "Revisar") -> 19.175 | G37: =IFERROR(F37*Datos!$B$3, "Revisar") -> 28.7625 | H37: =IFERROR(G37*Datos!$B$1, "Revisar") -> 16611.67 | I37: =IFERROR((VLOOKUP(B37, Roccia!$B$2:$D997, 3, FALSE) /(1-Datos!$E$1)), "Revisar") -> 21.071429 | J37: =IFERROR(I37*Datos!$B$3, "Revisar") -> 31.607143 | K37: =IFERROR(J37-G37, "Revisar") -> 2.8446429
A38: BALANZAS | B38: P021 | C38: BALANZA DE MOSTRADOR CAP 30KG DE ALTA PRECISION 905 | D38: =IF(MOD(F38, 5) <= 2.5, FLOOR(F38, 5), CEILING(F38, 5)) -> 45 | E38: =IF(MOD(G38, 5) <= 2.5, FLOOR(G38, 5), CEILING(G38, 5)) -> 65 | F38: =IFERROR((VLOOKUP(B38, Roccia!$B$2:$D997, 3, FALSE)*(1+Datos!$E$1)), "Revisar") -> 44.382 | G38: =IFERROR(F38*Datos!$B$3, "Revisar") -> 66.573 | H38: =IFERROR(G38*Datos!$B$1, "Revisar") -> 38448.977 | I38: =IFERROR((VLOOKUP(B38, Roccia!$B$2:$D997, 3, FALSE) /(1-Datos!$E$1)), "Revisar") -> 48.771429 | J38: =IFERROR(I38*Datos!$B$3, "Revisar") -> 73.157143 | K38: =IFERROR(J38-G38, "Revisar") -> 6.5841429
A39: BALANZAS | B39: P021S | C39: BALANZA DE MOSTRADOR CAP 30KG DE ALTA PRECISION 905 CON SENCAMER | D39: =IF(MOD(F39, 5) <= 2.5, FLOOR(F39, 5), CEILING(F39, 5)) -> 80 | E39: =IF(MOD(G39, 5) <= 2.5, FLOOR(G39, 5), CEILING(G39, 5)) -> 115 | F39: =IFERROR((VLOOKUP(B39, Roccia!$B$2:$D997, 3, FALSE)*(1+Datos!$E$1)), "Revisar") -> 78 | G39: =IFERROR(F39*Datos!$B$3, "Revisar") -> 117 | H39: =IFERROR(G39*Datos!$B$1, "Revisar") -> 67572.894 | I39: =IFERROR((VLOOKUP(B39, Roccia!$B$2:$D997, 3, FALSE) /(1-Datos!$E$1)), "Revisar") -> 85.714286 | J39: =IFERROR(I39*Datos!$B$3, "Revisar") -> 128.57143 | K39: =IFERROR(J39-G39, "Revisar") -> 11.571429
A40: BALANZAS | B40: P022 | C40: BALANZA DE MOSTRADOR CON SU VISOR CAP 30KG DE ALTA PRECISION 905ARM | D40: =IF(MOD(F40, 5) <= 2.5, FLOOR(F40, 5), CEILING(F40, 5)) -> 60 | E40: =IF(MOD(G40, 5) <= 2.5, FLOOR(G40, 5), CEILING(G40, 5)) -> 90 | F40: =IFERROR((VLOOKUP(B40, Roccia!$B$2:$D997, 3, FALSE)*(1+Datos!$E$1)), "Revisar") -> 58.734 | G40: =IFERROR(F40*Datos!$B$3, "Revisar") -> 88.101 | H40: =IFERROR(G40*Datos!$B$1, "Revisar") -> 50882.389 | I40: =IFERROR((VLOOKUP(B40, Roccia!$B$2:$D997, 3, FALSE) /(1-Datos!$E$1)), "Revisar") -> 64.542857 | J40: =IFERROR(I40*Datos!$B$3, "Revisar") -> 96.814286 | K40: =IFERROR(J40-G40, "Revisar") -> 8.7132857
A41: BALANZAS | B41: P023 | C41: ROMANA CAP 200KG DE ALTA PRECISION 616D | D41: =IF(MOD(F41, 5) <= 2.5, FLOOR(F41, 5), CEILING(F41, 5)) -> 90 | E41: =IF(MOD(G41, 5) <= 2.5, FLOOR(G41, 5), CEILING(G41, 5)) -> 135 | F41: =IFERROR((VLOOKUP(B41, Roccia!$B$2:$D997, 3, FALSE)*(1+Datos!$E$1)), "Revisar") -> 90.116 | G41: =IFERROR(F41*Datos!$B$3, "Revisar") -> 135.174 | H41: =IFERROR(G41*Datos!$B$1, "Revisar") -> 78069.217 | I41: =IFERROR((VLOOKUP(B41, Roccia!$B$2:$D997, 3, FALSE) /(1-Datos!$E$1)), "Revisar") -> 99.028571 | J41: =IFERROR(I41*Datos!$B$3, "Revisar") -> 148.54286 | K41: =IFERROR(J41-G41, "Revisar") -> 13.368857
A42: BALANZAS | B42: P024 | C42: ROMANA CAP 300KG DE ALTA PRECISION 617D | D42: =IF(MOD(F42, 5) <= 2.5, FLOOR(F42, 5), CEILING(F42, 5)) -> 125 | E42: =IF(MOD(G42, 5) <= 2.5, FLOOR(G42, 5), CEILING(G42, 5)) -> 185 | F42: =IFERROR((VLOOKUP(B42, Roccia!$B$2:$D997, 3, FALSE)*(1+Datos!$E$1)), "Revisar") -> 122.642 | G42: =IFERROR(F42*Datos!$B$3, "Revisar") -> 183.963 | H42: =IFERROR(G42*Datos!$B$1, "Revisar") -> 106247.11 | I42: =IFERROR((VLOOKUP(B42, Roccia!$B$2:$D997, 3, FALSE) /(1-Datos!$E$1)), "Revisar") -> 134.77143 | J42: =IFERROR(I42*Datos!$B$3, "Revisar") -> 202.15714 | K42: =IFERROR(J42-G42, "Revisar") -> 18.194143
A43: BALANZAS | B43: P025 | C43: ROMANA CAP 400KG DE ALTA PRECISION 618D | D43: =IF(MOD(F43, 5) <= 2.5, FLOOR(F43, 5), CEILING(F43, 5)) -> 155 | E43: =IF(MOD(G43, 5) <= 2.5, FLOOR(G43, 5), CEILING(G43, 5)) -> 235 | F43: =IFERROR((VLOOKUP(B43, Roccia!$B$2:$D997, 3, FALSE)*(1+Datos!$E$1)), "Revisar") -> 155.155 | G43: =IFERROR(F43*Datos!$B$3, "Revisar") -> 232.7325 | H43: =IFERROR(G43*Datos!$B$1, "Revisar") -> 134413.75 | I43: =IFERROR((VLOOKUP(B43, Roccia!$B$2:$D997, 3, FALSE) /(1-Datos!$E$1)), "Revisar") -> 170.5 | J43: =IFERROR(I43*Datos!$B$3, "Revisar") -> 255.75 | K43: =IFERROR(J43-G43, "Revisar") -> 23.0175
A44: BALANZAS | B44: P026 | C44: ROMANA DE ACERO INOXIDABLE CAP 200KG DE ALTA PRECISION RS-809 | D44: =IF(MOD(F44, 5) <= 2.5, FLOOR(F44, 5), CEILING(F44, 5)) -> 115 | E44: =IF(MOD(G44, 5) <= 2.5, FLOOR(G44, 5), CEILING(G44, 5)) -> 175 | F44: =IFERROR((VLOOKUP(B44, Roccia!$B$2:$D997, 3, FALSE)*(1+Datos!$E$1)), "Revisar") -> 117.312 | G44: =IFERROR(F44*Datos!$B$3, "Revisar") -> 175.968 | H44: =IFERROR(G44*Datos!$B$1, "Revisar") -> 101629.63 | I44: =IFERROR((VLOOKUP(B44, Roccia!$B$2:$D997, 3, FALSE) /(1-Datos!$E$1)), "Revisar") -> 128.91429 | J44: =IFERROR(I44*Datos!$B$3, "Revisar") -> 193.37143 | K44: =IFERROR(J44-G44, "Revisar") -> 17.403429
A45: BALANZAS | B45: P027 | C45: ROMANA DE ACERO INOXIDABLE CAP 300KG DE ALTA PRECISION RS-810 | D45: =IF(MOD(F45, 5) <= 2.5, FLOOR(F45, 5), CEILING(F45, 5)) -> 165 | E45: =IF(MOD(G45, 5) <= 2.5, FLOOR(G45, 5), CEILING(G45, 5)) -> 245 | F45: =IFERROR((VLOOKUP(B45, Roccia!$B$2:$D997, 3, FALSE)*(1+Datos!$E$1)), "Revisar") -> 163.813 | G45: =IFERROR(F45*Datos!$B$3, "Revisar") -> 245.7195 | H45: =IFERROR(G45*Datos!$B$1, "Revisar") -> 141914.34 | I45: =IFERROR((VLOOKUP(B45, Roccia!$B$2:$D997, 3, FALSE) /(1-Datos!$E$1)), "Revisar") -> 180.01429 | J45: =IFERROR(I45*Datos!$B$3, "Revisar") -> 270.02143 | K45: =IFERROR(J45-G45, "Revisar") -> 24.301929
A46: BALANZAS | B46: P028 | C46: ROMANA DE ACERO INOXIDABLE CAP 400KG DE ALTA PRECISION RS-811 | D46: =IF(MOD(F46, 5) <= 2.5, FLOOR(F46, 5), CEILING(F46, 5)) -> 210 | E46: =IF(MOD(G46, 5) <= 2.5, FLOOR(G46, 5), CEILING(G46, 5)) -> 315 | F46: =IFERROR((VLOOKUP(B46, Roccia!$B$2:$D997, 3, FALSE)*(1+Datos!$E$1)), "Revisar") -> 210.197 | G46: =IFERROR(F46*Datos!$B$3, "Revisar") -> 315.2955 | H46: =IFERROR(G46*Datos!$B$1, "Revisar") -> 182097.69 | I46: =IFERROR((VLOOKUP(B46, Roccia!$B$2:$D997, 3, FALSE) /(1-Datos!$E$1)), "Revisar") -> 230.98571 | J46: =IFERROR(I46*Datos!$B$3, "Revisar") -> 346.47857 | K46: =IFERROR(J46-G46, "Revisar") -> 31.183071
A47: BALANZAS | B47: P029 | C47: BALANZA MOSTRADOR ANTI-INSECTOS MODELO 969S | D47: =IF(MOD(F47, 5) <= 2.5, FLOOR(F47, 5), CEILING(F47, 5)) -> 55 | E47: =IF(MOD(G47, 5) <= 2.5, FLOOR(G47, 5), CEILING(G47, 5)) -> 80 | F47: =IFERROR((VLOOKUP(B47, Roccia!$B$2:$D997, 3, FALSE)*(1+Datos!$E$1)), "Revisar") -> 54.834 | G47: =IFERROR(F47*Datos!$B$3, "Revisar") -> 82.251 | H47: =IFERROR(G47*Datos!$B$1, "Revisar") -> 47503.744 | I47: =IFERROR((VLOOKUP(B47, Roccia!$B$2:$D997, 3, FALSE) /(1-Datos!$E$1)), "Revisar") -> 60.257143 | J47: =IFERROR(I47*Datos!$B$3, "Revisar") -> 90.385714 | K47: =IFERROR(J47-G47, "Revisar") -> 8.1347143
A48: BALANZAS | B48: P029S | C48: BALANZA MOSTRADOR ANTI-INSECTOS MODELO 969S CON SENCAMER | D48: =IF(MOD(F48, 5) <= 2.5, FLOOR(F48, 5), CEILING(F48, 5)) -> 85 | E48: =IF(MOD(G48, 5) <= 2.5, FLOOR(G48, 5), CEILING(G48, 5)) -> 130 | F48: =IFERROR((VLOOKUP(B48, Roccia!$B$2:$D997, 3, FALSE)*(1+Datos!$E$1)), "Revisar") -> 87.334 | G48: =IFERROR(F48*Datos!$B$3, "Revisar") -> 131.001 | H48: =IFERROR(G48*Datos!$B$1, "Revisar") -> 75659.117 | I48: =IFERROR((VLOOKUP(B48, Roccia!$B$2:$D997, 3, FALSE) /(1-Datos!$E$1)), "Revisar") -> 95.971429 | J48: =IFERROR(I48*Datos!$B$3, "Revisar") -> 143.95714 | K48: =IFERROR(J48-G48, "Revisar") -> 12.956143
A49: BALANZAS | B49: P030 | C49: BALANZA DE MOSTRADOR 30KG ETIQUETADORA CON SENCAMER ROP-30 ROCCIA | D49: =IF(MOD(F49, 5) <= 2.5, FLOOR(F49, 5), CEILING(F49, 5)) -> 630 | E49: =IF(MOD(G49, 5) <= 2.5, FLOOR(G49, 5), CEILING(G49, 5)) -> 940 | F49: =IFERROR((VLOOKUP(B49, Roccia!$B$2:$D997, 3, FALSE)*(1+Datos!$E$1)), "Revisar") -> 627.757 | G49: =IFERROR(F49*Datos!$B$3, "Revisar") -> 941.6355 | H49: =IFERROR(G49*Datos!$B$1, "Revisar") -> 543837.91 | I49: =IFERROR((VLOOKUP(B49, Roccia!$B$2:$D997, 3, FALSE) /(1-Datos!$E$1)), "Revisar") -> 689.84286 | J49: =IFERROR(I49*Datos!$B$3, "Revisar") -> 1034.7643 | K49: =IFERROR(J49-G49, "Revisar") -> 93.128786
A50: BOMBAS DE AGUA | B50: B001 | C50: BOMBA DE AGUA 1/2 HP | D50: =IF(MOD(F50, 5) <= 2.5, FLOOR(F50, 5), CEILING(F50, 5)) -> 35 | E50: =IF(MOD(G50, 5) <= 2.5, FLOOR(G50, 5), CEILING(G50, 5)) -> 50 | F50: =IFERROR((VLOOKUP(B50, Roccia!$B$2:$D997, 3, FALSE)*(1+Datos!$E$1)), "Revisar") -> 33.28 | G50: =IFERROR(F50*Datos!$B$3, "Revisar") -> 49.92 | H50: =IFERROR(G50*Datos!$B$1, "Revisar") -> 28831.101 | I50: =IFERROR((VLOOKUP(B50, Roccia!$B$2:$D997, 3, FALSE) /(1-Datos!$E$1)), "Revisar") -> 36.571429 | J50: =IFERROR(I50*Datos!$B$3, "Revisar") -> 54.857143 | K50: =IFERROR(J50-G50, "Revisar") -> 4.9371429
A51: BOMBAS DE AGUA | B51: B001C | C51: BOMBA DE AGUA DE 1/2HP PERIFÉRICA 110V ALTA GAMA 100% COBRE MARCA ROCCIA | D51: =IF(MOD(F51, 5) <= 2.5, FLOOR(F51, 5), CEILING(F51, 5)) -> 45 | E51: =IF(MOD(G51, 5) <= 2.5, FLOOR(G51, 5), CEILING(G51, 5)) -> 65 | F51: =IFERROR((VLOOKUP(B51, Roccia!$B$2:$D997, 3, FALSE)*(1+Datos!$E$1)), "Revisar") -> 42.835 | G51: =IFERROR(F51*Datos!$B$3, "Revisar") -> 64.2525 | H51: =IFERROR(G51*Datos!$B$1, "Revisar") -> 37108.781 | I51: =IFERROR((VLOOKUP(B51, Roccia!$B$2:$D997, 3, FALSE) /(1-Datos!$E$1)), "Revisar") -> 47.071429 | J51: =IFERROR(I51*Datos!$B$3, "Revisar") -> 70.607143 | K51: =IFERROR(J51-G51, "Revisar") -> 6.3546429
A52: BOMBAS DE AGUA | B52: B002 | C52: BOMBA DE AGUA 3/4 HP | D52: =IF(MOD(F52, 5) <= 2.5, FLOOR(F52, 5), CEILING(F52, 5)) -> 60 | E52: =IF(MOD(G52, 5) <= 2.5, FLOOR(G52, 5), CEILING(G52, 5)) -> 95 | F52: =IFERROR((VLOOKUP(B52, Roccia!$B$2:$D997, 3, FALSE)*(1+Datos!$E$1)), "Revisar") -> 61.776 | G52: =IFERROR(F52*Datos!$B$3, "Revisar") -> 92.664 | H52: =IFERROR(G52*Datos!$B$1, "Revisar") -> 53517.732 | I52: =IFERROR((VLOOKUP(B52, Roccia!$B$2:$D997, 3, FALSE) /(1-Datos!$E$1)), "Revisar") -> 67.885714 | J52: =IFERROR(I52*Datos!$B$3, "Revisar") -> 101.82857 | K52: =IFERROR(J52-G52, "Revisar") -> 9.1645714
A53: BOMBAS DE AGUA | B53: B002C | C53: BOMBA DE AGUA DE 3/4HP PERIFÉRICA 110V ALTA GAMA 100% COBRE MARCA ROCCIA | D53: =IF(MOD(F53, 5) <= 2.5, FLOOR(F53, 5), CEILING(F53, 5)) -> 70 | E53: =IF(MOD(G53, 5) <= 2.5, FLOOR(G53, 5), CEILING(G53, 5)) -> 105 | F53: =IFERROR((VLOOKUP(B53, Roccia!$B$2:$D997, 3, FALSE)*(1+Datos!$E$1)), "Revisar") -> 70.005 | G53: =IFERROR(F53*Datos!$B$3, "Revisar") -> 105.0075 | H53: =IFERROR(G53*Datos!$B$1, "Revisar") -> 60646.672 | I53: =IFERROR((VLOOKUP(B53, Roccia!$B$2:$D997, 3, FALSE) /(1-Datos!$E$1)), "Revisar") -> 76.928571 | J53: =IFERROR(I53*Datos!$B$3, "Revisar") -> 115.39286 | K53: =IFERROR(J53-G53, "Revisar") -> 10.385357
A54: BOMBAS DE AGUA | B54: B003 | C54: BOMBA DE AGUA 1 HP | D54: =IF(MOD(F54, 5) <= 2.5, FLOOR(F54, 5), CEILING(F54, 5)) -> 65 | E54: =IF(MOD(G54, 5) <= 2.5, FLOOR(G54, 5), CEILING(G54, 5)) -> 100 | F54: =IFERROR((VLOOKUP(B54, Roccia!$B$2:$D997, 3, FALSE)*(1+Datos!$E$1)), "Revisar") -> 66.872 | G54: =IFERROR(F54*Datos!$B$3, "Revisar") -> 100.308 | H54: =IFERROR(G54*Datos!$B$1, "Revisar") -> 57932.494 | I54: =IFERROR((VLOOKUP(B54, Roccia!$B$2:$D997, 3, FALSE) /(1-Datos!$E$1)), "Revisar") -> 73.485714 | J54: =IFERROR(I54*Datos!$B$3, "Revisar") -> 110.22857 | K54: =IFERROR(J54-G54, "Revisar") -> 9.9205714
A55: BOMBAS DE AGUA | B55: B003C | C55: BOMBA DE AGUA DE 1HP PERIFÉRICA 110V ALTA GAMA 100% COBRE MARCA ROCCIA | D55: =IF(MOD(F55, 5) <= 2.5, FLOOR(F55, 5), CEILING(F55, 5)) -> 75 | E55: =IF(MOD(G55, 5) <= 2.5, FLOOR(G55, 5), CEILING(G55, 5)) -> 115 | F55: =IFERROR((VLOOKUP(B55, Roccia!$B$2:$D997, 3, FALSE)*(1+Datos!$E$1)), "Revisar") -> 77.22 | G55: =IFERROR(F55*Datos!$B$3, "Revisar") -> 115.83 | H55: =IFERROR(G55*Datos!$B$1, "Revisar") -> 66897.165 | I55: =IFERROR((VLOOKUP(B55, Roccia!$B$2:$D997, 3, FALSE) /(1-Datos!$E$1)), "Revisar") -> 84.857143 | J55: =IFERROR(I55*Datos!$B$3, "Revisar") -> 127.28571 | K55: =IFERROR(J55-G55, "Revisar") -> 11.455714
A56: BOMBAS DE AGUA | B56: B004 | C56: BOMBA DE AGUA DE 2HP PERIFERICA AUTOCEBANTE TIPO JET 220V JET-200A MARCA ROCCIA | D56: =IF(MOD(F56, 5) <= 2.5, FLOOR(F56, 5), CEILING(F56, 5)) -> 230 | E56: =IF(MOD(G56, 5) <= 2.5, FLOOR(G56, 5), CEILING(G56, 5)) -> 345 | F56: =IFERROR((VLOOKUP(B56, Roccia!$B$2:$D997, 3, FALSE)*(1+Datos!$E$1)), "Revisar") -> 230.62 | G56: =IFERROR(F56*Datos!$B$3, "Revisar") -> 345.93 | H56: =IFERROR(G56*Datos!$B$1, "Revisar") -> 199790.52 | I56: =IFERROR((VLOOKUP(B56, Roccia!$B$2:$D997, 3, FALSE) /(1-Datos!$E$1)), "Revisar") -> 253.42857 | J56: =IFERROR(I56*Datos!$B$3, "Revisar") -> 380.14286 | K56: =IFERROR(J56-G56, "Revisar") -> 34.212857
A57: BOMBAS DE AGUA | B57: B005 | C57: PRESS CONTROL INTELIGENTE | D57: =IF(MOD(F57, 5) <= 2.5, FLOOR(F57, 5), CEILING(F57, 5)) -> 30 | E57: =IF(MOD(G57, 5) <= 2.5, FLOOR(G57, 5), CEILING(G57, 5)) -> 45 | F57: =IFERROR((VLOOKUP(B57, Roccia!$B$2:$D997, 3, FALSE)*(1+Datos!$E$1)), "Revisar") -> 29.38 | G57: =IFERROR(F57*Datos!$B$3, "Revisar") -> 44.07 | H57: =IFERROR(G57*Datos!$B$1, "Revisar") -> 25452.457 | I57: =IFERROR((VLOOKUP(B57, Roccia!$B$2:$D997, 3, FALSE) /(1-Datos!$E$1)), "Revisar") -> 32.285714 | J57: =IFERROR(I57*Datos!$B$3, "Revisar") -> 48.428571 | K57: =IFERROR(J57-G57, "Revisar") -> 4.3585714
A58: BOMBAS DE AGUA | B58: B006 | C58: PURIFICADOR DE AGUA INTELIGENTE OSMOSIS INVERSA 96W 1,58L/M RO700P | D58: =IF(MOD(F58, 5) <= 2.5, FLOOR(F58, 5), CEILING(F58, 5)) -> 370 | E58: =IF(MOD(G58, 5) <= 2.5, FLOOR(G58, 5), CEILING(G58, 5)) -> 555 | F58: =IFERROR((VLOOKUP(B58, Roccia!$B$2:$D997, 3, FALSE)*(1+Datos!$E$1)), "Revisar") -> 369.772 | G58: =IFERROR(F58*Datos!$B$3, "Revisar") -> 554.658 | H58: =IFERROR(G58*Datos!$B$1, "Revisar") -> 320340.56 | I58: =IFERROR((VLOOKUP(B58, Roccia!$B$2:$D997, 3, FALSE) /(1-Datos!$E$1)), "Revisar") -> 406.34286 | J58: =IFERROR(I58*Datos!$B$3, "Revisar") -> 609.51429 | K58: =IFERROR(J58-G58, "Revisar") -> 54.856286
A59: BOMBAS DE AGUA | B59: B007 | C59: REPUESTO FILTRO DE AGUA PCT FILTRO | D59: =IF(MOD(F59, 5) <= 2.5, FLOOR(F59, 5), CEILING(F59, 5)) -> 50 | E59: =IF(MOD(G59, 5) <= 2.5, FLOOR(G59, 5), CEILING(G59, 5)) -> 75 | F59: =IFERROR((VLOOKUP(B59, Roccia!$B$2:$D997, 3, FALSE)*(1+Datos!$E$1)), "Revisar") -> 51.129 | G59: =IFERROR(F59*Datos!$B$3, "Revisar") -> 76.6935 | H59: =IFERROR(G59*Datos!$B$1, "Revisar") -> 44294.032 | I59: =IFERROR((VLOOKUP(B59, Roccia!$B$2:$D997, 3, FALSE) /(1-Datos!$E$1)), "Revisar") -> 56.185714 | J59: =IFERROR(I59*Datos!$B$3, "Revisar") -> 84.278571 | K59: =IFERROR(J59-G59, "Revisar") -> 7.5850714
A60: BOMBAS DE AGUA | B60: B008 | C60: REPUESTO FILTRO DE AGUA 600G RO MEMBRANA | D60: =IF(MOD(F60, 5) <= 2.5, FLOOR(F60, 5), CEILING(F60, 5)) -> 75 | E60: =IF(MOD(G60, 5) <= 2.5, FLOOR(G60, 5), CEILING(G60, 5)) -> 115 | F60: =IFERROR((VLOOKUP(B60, Roccia!$B$2:$D997, 3, FALSE)*(1+Datos!$E$1)), "Revisar") -> 76.921 | G60: =IFERROR(F60*Datos!$B$3, "Revisar") -> 115.3815 | H60: =IFERROR(G60*Datos!$B$1, "Revisar") -> 66638.135 | I60: =IFERROR((VLOOKUP(B60, Roccia!$B$2:$D997, 3, FALSE) /(1-Datos!$E$1)), "Revisar") -> 84.528571 | J60: =IFERROR(I60*Datos!$B$3, "Revisar") -> 126.79286 | K60: =IFERROR(J60-G60, "Revisar") -> 11.411357
A61: BOMBAS DE AGUA CENTRIFUGAS Y PISCINA | B61: B012C | C61: BOMBA DE AGUA CENTRIFUGA DE 1HP HCM158 110V | D61: =IF(MOD(F61, 5) <= 2.5, FLOOR(F61, 5), CEILING(F61, 5)) -> 110 | E61: =IF(MOD(G61, 5) <= 2.5, FLOOR(G61, 5), CEILING(G61, 5)) -> 165 | F61: =IFERROR((VLOOKUP(B61, Roccia!$B$2:$D997, 3, FALSE)*(1+Datos!$E$1)), "Revisar") -> 111.527 | G61: =IFERROR(F61*Datos!$B$3, "Revisar") -> 167.2905 | H61: =IFERROR(G61*Datos!$B$1, "Revisar") -> 96617.976 | I61: =IFERROR((VLOOKUP(B61, Roccia!$B$2:$D997, 3, FALSE) /(1-Datos!$E$1)), "Revisar") -> 122.55714 | J61: =IFERROR(I61*Datos!$B$3, "Revisar") -> 183.83571 | K61: =IFERROR(J61-G61, "Revisar") -> 16.545214
A62: BOMBAS DE AGUA CENTRIFUGAS Y PISCINA | B62: B013C | C62: BOMBA DE AGUA CENTRIFUGA DE 1.5HP HCM180 110V | D62: =IF(MOD(F62, 5) <= 2.5, FLOOR(F62, 5), CEILING(F62, 5)) -> 180 | E62: =IF(MOD(G62, 5) <= 2.5, FLOOR(G62, 5), CEILING(G62, 5)) -> 270 | F62: =IFERROR((VLOOKUP(B62, Roccia!$B$2:$D997, 3, FALSE)*(1+Datos!$E$1)), "Revisar") -> 180.778 | G62: =IFERROR(F62*Datos!$B$3, "Revisar") -> 271.167 | H62: =IFERROR(G62*Datos!$B$1, "Revisar") -> 156611.44 | I62: =IFERROR((VLOOKUP(B62, Roccia!$B$2:$D997, 3, FALSE) /(1-Datos!$E$1)), "Revisar") -> 198.65714 | J62: =IFERROR(I62*Datos!$B$3, "Revisar") -> 297.98571 | K62: =IFERROR(J62-G62, "Revisar") -> 26.818714
A63: BOMBAS DE AGUA CENTRIFUGAS Y PISCINA | B63: B014C | C63: BOMBA DE AGUA CENTRIFUGA DE 2HP HCM190 220V | D63: =IF(MOD(F63, 5) <= 2.5, FLOOR(F63, 5), CEILING(F63, 5)) -> 190 | E63: =IF(MOD(G63, 5) <= 2.5, FLOOR(G63, 5), CEILING(G63, 5)) -> 280 | F63: =IFERROR((VLOOKUP(B63, Roccia!$B$2:$D997, 3, FALSE)*(1+Datos!$E$1)), "Revisar") -> 188.019 | G63: =IFERROR(F63*Datos!$B$3, "Revisar") -> 282.0285 | H63: =IFERROR(G63*Datos!$B$1, "Revisar") -> 162884.46 | I63: =IFERROR((VLOOKUP(B63, Roccia!$B$2:$D997, 3, FALSE) /(1-Datos!$E$1)), "Revisar") -> 206.61429 | J63: =IFERROR(I63*Datos!$B$3, "Revisar") -> 309.92143 | K63: =IFERROR(J63-G63, "Revisar") -> 27.892929
A64: BOMBAS DE AGUA CENTRIFUGAS Y PISCINA | B64: B015C | C64: BOMBA DE AGUA CENTRIFUGA DE 3HP HCM200 220V | D64: =IF(MOD(F64, 5) <= 2.5, FLOOR(F64, 5), CEILING(F64, 5)) -> 195 | E64: =IF(MOD(G64, 5) <= 2.5, FLOOR(G64, 5), CEILING(G64, 5)) -> 295 | F64: =IFERROR((VLOOKUP(B64, Roccia!$B$2:$D997, 3, FALSE)*(1+Datos!$E$1)), "Revisar") -> 195.429 | G64: =IFERROR(F64*Datos!$B$3, "Revisar") -> 293.1435 | H64: =IFERROR(G64*Datos!$B$1, "Revisar") -> 169303.89 | I64: =IFERROR((VLOOKUP(B64, Roccia!$B$2:$D997, 3, FALSE) /(1-Datos!$E$1)), "Revisar") -> 214.75714 | J64: =IFERROR(I64*Datos!$B$3, "Revisar") -> 322.13571 | K64: =IFERROR(J64-G64, "Revisar") -> 28.992214
A65: BOMBAS DE AGUA CENTRIFUGAS Y PISCINA | B65: B016C | C65: BOMBA CENTRIFUGA IMPULSOR TRIFASICA 4KW 5.5HP HST40-160/40 | D65: =IF(MOD(F65, 5) <= 2.5, FLOOR(F65, 5), CEILING(F65, 5)) -> 635 | E65: =IF(MOD(G65, 5) <= 2.5, FLOOR(G65, 5), CEILING(G65, 5)) -> 955 | F65: =IFERROR((VLOOKUP(B65, Roccia!$B$2:$D997, 3, FALSE)*(1+Datos!$E$1)), "Revisar") -> 637.078 | G65: =IFERROR(F65*Datos!$B$3, "Revisar") -> 955.617 | H65: =IFERROR(G65*Datos!$B$1, "Revisar") -> 551912.87 | I65: =IFERROR((VLOOKUP(B65, Roccia!$B$2:$D997, 3, FALSE) /(1-Datos!$E$1)), "Revisar") -> 700.08571 | J65: =IFERROR(I65*Datos!$B$3, "Revisar") -> 1050.1286 | K65: =IFERROR(J65-G65, "Revisar") -> 94.511571
A66: BOMBAS DE AGUA CENTRIFUGAS Y PISCINA | B66: B017C | C66: BOMBA CENTRIFUGA IMPULSOR TRIFASICA 5.5KW 7.5HP HST40-200/55 | D66: =IF(MOD(F66, 5) <= 2.5, FLOOR(F66, 5), CEILING(F66, 5)) -> 810 | E66: =IF(MOD(G66, 5) <= 2.5, FLOOR(G66, 5), CEILING(G66, 5)) -> 1215 | F66: =IFERROR((VLOOKUP(B66, Roccia!$B$2:$D997, 3, FALSE)*(1+Datos!$E$1)), "Revisar") -> 808.34 | G66: =IFERROR(F66*Datos!$B$3, "Revisar") -> 1212.51 | H66: =IFERROR(G66*Datos!$B$1, "Revisar") -> 700280.42 | I66: =IFERROR((VLOOKUP(B66, Roccia!$B$2:$D997, 3, FALSE) /(1-Datos!$E$1)), "Revisar") -> 888.28571 | J66: =IFERROR(I66*Datos!$B$3, "Revisar") -> 1332.4286 | K66: =IFERROR(J66-G66, "Revisar") -> 119.91857
A67: BOMBAS DE AGUA CENTRIFUGAS Y PISCINA | B67: B018C | C67: BOMBA CENTRIFUGA IMPULSOR TRIFASICA 7.5KW 10HP HST40-200/75 | D67: =IF(MOD(F67, 5) <= 2.5, FLOOR(F67, 5), CEILING(F67, 5)) -> 850 | E67: =IF(MOD(G67, 5) <= 2.5, FLOOR(G67, 5), CEILING(G67, 5)) -> 1270 | F67: =IFERROR((VLOOKUP(B67, Roccia!$B$2:$D997, 3, FALSE)*(1+Datos!$E$1)), "Revisar") -> 847.574 | G67: =IFERROR(F67*Datos!$B$3, "Revisar") -> 1271.361 | H67: =IFERROR(G67*Datos!$B$1, "Revisar") -> 734269.59 | I67: =IFERROR((VLOOKUP(B67, Roccia!$B$2:$D997, 3, FALSE) /(1-Datos!$E$1)), "Revisar") -> 931.4 | J67: =IFERROR(I67*Datos!$B$3, "Revisar") -> 1397.1 | K67: =IFERROR(J67-G67, "Revisar") -> 125.739
A68: BOMBAS DE AGUA CENTRIFUGAS Y PISCINA | B68: B019C | C68: BOMBA CENTRIFUGA IMPULSOR TRIFASICA 15KW 20HP HST40-250/150 | D68: =IF(MOD(F68, 5) <= 2.5, FLOOR(F68, 5), CEILING(F68, 5)) -> 1655 | E68: =IF(MOD(G68, 5) <= 2.5, FLOOR(G68, 5), CEILING(G68, 5)) -> 2480 | F68: =IFERROR((VLOOKUP(B68, Roccia!$B$2:$D997, 3, FALSE)*(1+Datos!$E$1)), "Revisar") -> 1653.054 | G68: =IFERROR(F68*Datos!$B$3, "Revisar") -> 2479.581 | H68: =IFERROR(G68*Datos!$B$1, "Revisar") -> 1432072.3 | I68: =IFERROR((VLOOKUP(B68, Roccia!$B$2:$D997, 3, FALSE) /(1-Datos!$E$1)), "Revisar") -> 1816.5429 | J68: =IFERROR(I68*Datos!$B$3, "Revisar") -> 2724.8143 | K68: =IFERROR(J68-G68, "Revisar") -> 245.23329
A69: BOMBAS DE AGUA CENTRIFUGAS Y PISCINA | B69: B020C | C69: BOMBA CENTRIFUGA DOBLE IMPULSOR TRIFASICA 5.5KW 7.5HP HST32-250/55D | D69: =IF(MOD(F69, 5) <= 2.5, FLOOR(F69, 5), CEILING(F69, 5)) -> 1005 | E69: =IF(MOD(G69, 5) <= 2.5, FLOOR(G69, 5), CEILING(G69, 5)) -> 1510 | F69: =IFERROR((VLOOKUP(B69, Roccia!$B$2:$D997, 3, FALSE)*(1+Datos!$E$1)), "Revisar") -> 1007.409 | G69: =IFERROR(F69*Datos!$B$3, "Revisar") -> 1511.1135 | H69: =IFERROR(G69*Datos!$B$1, "Revisar") -> 872737.71 | I69: =IFERROR((VLOOKUP(B69, Roccia!$B$2:$D997, 3, FALSE) /(1-Datos!$E$1)), "Revisar") -> 1107.0429 | J69: =IFERROR(I69*Datos!$B$3, "Revisar") -> 1660.5643 | K69: =IFERROR(J69-G69, "Revisar") -> 149.45079
A70: BOMBAS DE AGUA CENTRIFUGAS Y PISCINA | B70: B021C | C70: BOMBA CENTRIFUGA DOBLE IMPULSOR TRIFASICA 7.5KW 10HP HST32-250/75D | D70: =IF(MOD(F70, 5) <= 2.5, FLOOR(F70, 5), CEILING(F70, 5)) -> 1055 | E70: =IF(MOD(G70, 5) <= 2.5, FLOOR(G70, 5), CEILING(G70, 5)) -> 1585 | F70: =IFERROR((VLOOKUP(B70, Roccia!$B$2:$D997, 3, FALSE)*(1+Datos!$E$1)), "Revisar") -> 1057.303 | G70: =IFERROR(F70*Datos!$B$3, "Revisar") -> 1585.9545 | H70: =IFERROR(G70*Datos!$B$1, "Revisar") -> 915961.84 | I70: =IFERROR((VLOOKUP(B70, Roccia!$B$2:$D997, 3, FALSE) /(1-Datos!$E$1)), "Revisar") -> 1161.8714 | J70: =IFERROR(I70*Datos!$B$3, "Revisar") -> 1742.8071 | K70: =IFERROR(J70-G70, "Revisar") -> 156.85264
A71: BOMBAS DE AGUA CENTRIFUGAS Y PISCINA | B71: B017P | C71: BOMBA DE AGUA DE 3/4HP DE PISCINAS HFC-552 220V MARCA ROCCIA | D71: =IF(MOD(F71, 5) <= 2.5, FLOOR(F71, 5), CEILING(F71, 5)) -> 125 | E71: =IF(MOD(G71, 5) <= 2.5, FLOOR(G71, 5), CEILING(G71, 5)) -> 190 | F71: =IFERROR((VLOOKUP(B71, Roccia!$B$2:$D997, 3, FALSE)*(1+Datos!$E$1)), "Revisar") -> 126.087 | G71: =IFERROR(F71*Datos!$B$3, "Revisar") -> 189.1305 | H71: =IFERROR(G71*Datos!$B$1, "Revisar") -> 109231.58 | I71: =IFERROR((VLOOKUP(B71, Roccia!$B$2:$D997, 3, FALSE) /(1-Datos!$E$1)), "Revisar") -> 138.55714 | J71: =IFERROR(I71*Datos!$B$3, "Revisar") -> 207.83571 | K71: =IFERROR(J71-G71, "Revisar") -> 18.705214
A72: BOMBAS DE AGUA CENTRIFUGAS Y PISCINA | B72: B020P | C72: BOMBA DE AGUA PARA PISCINA DE 1.5HP NEW MODEL HFC-1101 220V | D72: =IF(MOD(F72, 5) <= 2.5, FLOOR(F72, 5), CEILING(F72, 5)) -> 170 | E72: =IF(MOD(G72, 5) <= 2.5, FLOOR(G72, 5), CEILING(G72, 5)) -> 255 | F72: =IFERROR((VLOOKUP(B72, Roccia!$B$2:$D997, 3, FALSE)*(1+Datos!$E$1)), "Revisar") -> 169.676 | G72: =IFERROR(F72*Datos!$B$3, "Revisar") -> 254.514 | H72: =IFERROR(G72*Datos!$B$1, "Revisar") -> 146993.57 | I72: =IFERROR((VLOOKUP(B72, Roccia!$B$2:$D997, 3, FALSE) /(1-Datos!$E$1)), "Revisar") -> 186.45714 | J72: =IFERROR(I72*Datos!$B$3, "Revisar") -> 279.68571 | K72: =IFERROR(J72-G72, "Revisar") -> 25.171714
A73: BOMBAS DE AGUA CENTRIFUGAS Y PISCINA | B73: B021P | C73: BOMBA DE AGUA PARA PISCINA DE 2.0HP NEW MODEL HFC-1501 220V | D73: =IF(MOD(F73, 5) <= 2.5, FLOOR(F73, 5), CEILING(F73, 5)) -> 220 | E73: =IF(MOD(G73, 5) <= 2.5, FLOOR(G73, 5), CEILING(G73, 5)) -> 330 | F73: =IFERROR((VLOOKUP(B73, Roccia!$B$2:$D997, 3, FALSE)*(1+Datos!$E$1)), "Revisar") -> 218.543 | G73: =IFERROR(F73*Datos!$B$3, "Revisar") -> 327.8145 | H73: =IFERROR(G73*Datos!$B$1, "Revisar") -> 189327.99 | I73: =IFERROR((VLOOKUP(B73, Roccia!$B$2:$D997, 3, FALSE) /(1-Datos!$E$1)), "Revisar") -> 240.15714 | J73: =IFERROR(I73*Datos!$B$3, "Revisar") -> 360.23571 | K73: =IFERROR(J73-G73, "Revisar") -> 32.421214
A74: BOMBAS DE AGUA CENTRIFUGAS Y PISCINA | B74: B022P | C74: BOMBA DE AGUA PARA PISCINA DE 3.0HP NEW MODEL HFC-2201 220V | D74: =IF(MOD(F74, 5) <= 2.5, FLOOR(F74, 5), CEILING(F74, 5)) -> 285 | E74: =IF(MOD(G74, 5) <= 2.5, FLOOR(G74, 5), CEILING(G74, 5)) -> 425 | F74: =IFERROR((VLOOKUP(B74, Roccia!$B$2:$D997, 3, FALSE)*(1+Datos!$E$1)), "Revisar") -> 283.4 | G74: =IFERROR(F74*Datos!$B$3, "Revisar") -> 425.1 | H74: =IFERROR(G74*Datos!$B$1, "Revisar") -> 245514.85 | I74: =IFERROR((VLOOKUP(B74, Roccia!$B$2:$D997, 3, FALSE) /(1-Datos!$E$1)), "Revisar") -> 311.42857 | J74: =IFERROR(I74*Datos!$B$3, "Revisar") -> 467.14286 | K74: =IFERROR(J74-G74, "Revisar") -> 42.042857
A75: BOMBAS DE AGUA CENTRIFUGAS Y PISCINA | B75: B019AI | C75: BOMBA DE AGUA CENTRIFUGA CON IMPULSOR DE ACERO INOXIDABLE 1HP HCT-26S | D75: =IF(MOD(F75, 5) <= 2.5, FLOOR(F75, 5), CEILING(F75, 5)) -> 140 | E75: =IF(MOD(G75, 5) <= 2.5, FLOOR(G75, 5), CEILING(G75, 5)) -> 210 | F75: =IFERROR((VLOOKUP(B75, Roccia!$B$2:$D997, 3, FALSE)*(1+Datos!$E$1)), "Revisar") -> 140.478 | G75: =IFERROR(F75*Datos!$B$3, "Revisar") -> 210.717 | H75: =IFERROR(G75*Datos!$B$1, "Revisar") -> 121698.78 | I75: =IFERROR((VLOOKUP(B75, Roccia!$B$2:$D997, 3, FALSE) /(1-Datos!$E$1)), "Revisar") -> 154.37143 | J75: =IFERROR(I75*Datos!$B$3, "Revisar") -> 231.55714 | K75: =IFERROR(J75-G75, "Revisar") -> 20.840143
A76: BOMBAS DE AGUA CENTRIFUGAS Y PISCINA | B76: B023C | C76: MOTOBOMBA 2¨ A GASOLINA MARCA ROCCIA GOOD QUALITY | D76: =IF(MOD(F76, 5) <= 2.5, FLOOR(F76, 5), CEILING(F76, 5)) -> 245 | E76: =IF(MOD(G76, 5) <= 2.5, FLOOR(G76, 5), CEILING(G76, 5)) -> 365 | F76: =IFERROR((VLOOKUP(B76, Roccia!$B$2:$D997, 3, FALSE)*(1+Datos!$E$1)), "Revisar") -> 244.049 | G76: =IFERROR(F76*Datos!$B$3, "Revisar") -> 366.0735 | H76: =IFERROR(G76*Datos!$B$1, "Revisar") -> 211424.32 | I76: =IFERROR((VLOOKUP(B76, Roccia!$B$2:$D997, 3, FALSE) /(1-Datos!$E$1)), "Revisar") -> 268.18571 | J76: =IFERROR(I76*Datos!$B$3, "Revisar") -> 402.27857 | K76: =IFERROR(J76-G76, "Revisar") -> 36.205071
A77: BOMBAS DE AGUA CENTRIFUGAS Y PISCINA | B77: B024C | C77: MOTOBOMBA 3¨ A GASOLINA MARCA ROCCIA GOOD QUALITY | D77: =IF(MOD(F77, 5) <= 2.5, FLOOR(F77, 5), CEILING(F77, 5)) -> 270 | E77: =IF(MOD(G77, 5) <= 2.5, FLOOR(G77, 5), CEILING(G77, 5)) -> 410 | F77: =IFERROR((VLOOKUP(B77, Roccia!$B$2:$D997, 3, FALSE)*(1+Datos!$E$1)), "Revisar") -> 271.687 | G77: =IFERROR(F77*Datos!$B$3, "Revisar") -> 407.5305 | H77: =IFERROR(G77*Datos!$B$1, "Revisar") -> 235367.65 | I77: =IFERROR((VLOOKUP(B77, Roccia!$B$2:$D997, 3, FALSE) /(1-Datos!$E$1)), "Revisar") -> 298.55714 | J77: =IFERROR(I77*Datos!$B$3, "Revisar") -> 447.83571 | K77: =IFERROR(J77-G77, "Revisar") -> 40.305214
A78: BOMBAS DE AGUA CENTRIFUGAS Y PISCINA | B78: B001A | C78: BOMBA DE AGUA DE 1HP DE ACHIQUE WQD750-B MARCA ROCCIA | D78: =IF(MOD(F78, 5) <= 2.5, FLOOR(F78, 5), CEILING(F78, 5)) -> 135 | E78: =IF(MOD(G78, 5) <= 2.5, FLOOR(G78, 5), CEILING(G78, 5)) -> 200 | F78: =IFERROR((VLOOKUP(B78, Roccia!$B$2:$D997, 3, FALSE)*(1+Datos!$E$1)), "Revisar") -> 134.81 | G78: =IFERROR(F78*Datos!$B$3, "Revisar") -> 202.215 | H78: =IFERROR(G78*Datos!$B$1, "Revisar") -> 116788.48 | I78: =IFERROR((VLOOKUP(B78, Roccia!$B$2:$D997, 3, FALSE) /(1-Datos!$E$1)), "Revisar") -> 148.14286 | J78: =IFERROR(I78*Datos!$B$3, "Revisar") -> 222.21429 | K78: =IFERROR(J78-G78, "Revisar") -> 19.999286
A79: BOMBAS DE AGUA SUMERGIBLES | B79: B006S | C79: BOMBA DE AGUA SUMERGIBLE DE 1/2HP 3SE2/9 110V | D79: =IF(MOD(F79, 5) <= 2.5, FLOOR(F79, 5), CEILING(F79, 5)) -> 155 | E79: =IF(MOD(G79, 5) <= 2.5, FLOOR(G79, 5), CEILING(G79, 5)) -> 235 | F79: =IFERROR((VLOOKUP(B79, Roccia!$B$2:$D997, 3, FALSE)*(1+Datos!$E$1)), "Revisar") -> 155.207 | G79: =IFERROR(F79*Datos!$B$3, "Revisar") -> 232.8105 | H79: =IFERROR(G79*Datos!$B$1, "Revisar") -> 134458.8 | I79: =IFERROR((VLOOKUP(B79, Roccia!$B$2:$D997, 3, FALSE) /(1-Datos!$E$1)), "Revisar") -> 170.55714 | J79: =IFERROR(I79*Datos!$B$3, "Revisar") -> 255.83571 | K79: =IFERROR(J79-G79, "Revisar") -> 23.025214
A80: BOMBAS DE AGUA SUMERGIBLES | B80: B007S | C80: BOMBA DE AGUA SUMERGIBLE DE 1/2HP 3SE2/9 220V | D80: =IF(MOD(F80, 5) <= 2.5, FLOOR(F80, 5), CEILING(F80, 5)) -> 155 | E80: =IF(MOD(G80, 5) <= 2.5, FLOOR(G80, 5), CEILING(G80, 5)) -> 235 | F80: =IFERROR((VLOOKUP(B80, Roccia!$B$2:$D997, 3, FALSE)*(1+Datos!$E$1)), "Revisar") -> 155.207 | G80: =IFERROR(F80*Datos!$B$3, "Revisar") -> 232.8105 | H80: =IFERROR(G80*Datos!$B$1, "Revisar") -> 134458.8 | I80: =IFERROR((VLOOKUP(B80, Roccia!$B$2:$D997, 3, FALSE) /(1-Datos!$E$1)), "Revisar") -> 170.55714 | J80: =IFERROR(I80*Datos!$B$3, "Revisar") -> 255.83571 | K80: =IFERROR(J80-G80, "Revisar") -> 23.025214
A81: BOMBAS DE AGUA SUMERGIBLES | B81: B008S | C81: BOMBA DE AGUA SUMERGIBLE DE 3/4HP 3SE2-13 220V | D81: =IF(MOD(F81, 5) <= 2.5, FLOOR(F81, 5), CEILING(F81, 5)) -> 160 | E81: =IF(MOD(G81, 5) <= 2.5, FLOOR(G81, 5), CEILING(G81, 5)) -> 240 | F81: =IFERROR((VLOOKUP(B81, Roccia!$B$2:$D997, 3, FALSE)*(1+Datos!$E$1)), "Revisar") -> 160.186 | G81: =IFERROR(F81*Datos!$B$3, "Revisar") -> 240.279 | H81: =IFERROR(G81*Datos!$B$1, "Revisar") -> 138772.2 | I81: =IFERROR((VLOOKUP(B81, Roccia!$B$2:$D997, 3, FALSE) /(1-Datos!$E$1)), "Revisar") -> 176.02857 | J81: =IFERROR(I81*Datos!$B$3, "Revisar") -> 264.04286 | K81: =IFERROR(J81-G81, "Revisar") -> 23.763857
A82: BOMBAS DE AGUA SUMERGIBLES | B82: B009S | C82: BOMBA DE AGUA SUMERGIBLE DE 1HP 3SE2-17 220V | D82: =IF(MOD(F82, 5) <= 2.5, FLOOR(F82, 5), CEILING(F82, 5)) -> 185 | E82: =IF(MOD(G82, 5) <= 2.5, FLOOR(G82, 5), CEILING(G82, 5)) -> 275 | F82: =IFERROR((VLOOKUP(B82, Roccia!$B$2:$D997, 3, FALSE)*(1+Datos!$E$1)), "Revisar") -> 183.365 | G82: =IFERROR(F82*Datos!$B$3, "Revisar") -> 275.0475 | H82: =IFERROR(G82*Datos!$B$1, "Revisar") -> 158852.61 | I82: =IFERROR((VLOOKUP(B82, Roccia!$B$2:$D997, 3, FALSE) /(1-Datos!$E$1)), "Revisar") -> 201.5 | J82: =IFERROR(I82*Datos!$B$3, "Revisar") -> 302.25 | K82: =IFERROR(J82-G82, "Revisar") -> 27.2025
A83: BOMBAS DE AGUA SUMERGIBLES | B83: B010S | C83: BOMBA DE AGUA SUMERGIBLE DE 1.5HP 4SE3-13 220V | D83: =IF(MOD(F83, 5) <= 2.5, FLOOR(F83, 5), CEILING(F83, 5)) -> 235 | E83: =IF(MOD(G83, 5) <= 2.5, FLOOR(G83, 5), CEILING(G83, 5)) -> 350 | F83: =IFERROR((VLOOKUP(B83, Roccia!$B$2:$D997, 3, FALSE)*(1+Datos!$E$1)), "Revisar") -> 234.273 | G83: =IFERROR(F83*Datos!$B$3, "Revisar") -> 351.4095 | H83: =IFERROR(G83*Datos!$B$1, "Revisar") -> 202955.19 | I83: =IFERROR((VLOOKUP(B83, Roccia!$B$2:$D997, 3, FALSE) /(1-Datos!$E$1)), "Revisar") -> 257.44286 | J83: =IFERROR(I83*Datos!$B$3, "Revisar") -> 386.16429 | K83: =IFERROR(J83-G83, "Revisar") -> 34.754786
A84: BOMBAS DE AGUA SUMERGIBLES | B84: B011S | C84: BOMBA DE AGUA SUMERGIBLE DE 2HP 4SE3-17 220V | D84: =IF(MOD(F84, 5) <= 2.5, FLOOR(F84, 5), CEILING(F84, 5)) -> 280 | E84: =IF(MOD(G84, 5) <= 2.5, FLOOR(G84, 5), CEILING(G84, 5)) -> 415 | F84: =IFERROR((VLOOKUP(B84, Roccia!$B$2:$D997, 3, FALSE)*(1+Datos!$E$1)), "Revisar") -> 277.94 | G84: =IFERROR(F84*Datos!$B$3, "Revisar") -> 416.91 | H84: =IFERROR(G84*Datos!$B$1, "Revisar") -> 240784.74 | I84: =IFERROR((VLOOKUP(B84, Roccia!$B$2:$D997, 3, FALSE) /(1-Datos!$E$1)), "Revisar") -> 305.42857 | J84: =IFERROR(I84*Datos!$B$3, "Revisar") -> 458.14286 | K84: =IFERROR(J84-G84, "Revisar") -> 41.232857
A85: BOMBAS DE AGUA SUMERGIBLES | B85: B012S | C85: BOMBA DE AGUA DE 5.5HP SUMERGIBLE TRIFÁSICA MARCA ROCCIA | D85: =IF(MOD(F85, 5) <= 2.5, FLOOR(F85, 5), CEILING(F85, 5)) -> 420 | E85: =IF(MOD(G85, 5) <= 2.5, FLOOR(G85, 5), CEILING(G85, 5)) -> 625 | F85: =IFERROR((VLOOKUP(B85, Roccia!$B$2:$D997, 3, FALSE)*(1+Datos!$E$1)), "Revisar") -> 417.638 | G85: =IFERROR(F85*Datos!$B$3, "Revisar") -> 626.457 | H85: =IFERROR(G85*Datos!$B$1, "Revisar") -> 361807.8 | I85: =IFERROR((VLOOKUP(B85, Roccia!$B$2:$D997, 3, FALSE) /(1-Datos!$E$1)), "Revisar") -> 458.94286 | J85: =IFERROR(I85*Datos!$B$3, "Revisar") -> 688.41429 | K85: =IFERROR(J85-G85, "Revisar") -> 61.957286
A86: BOMBAS DE AGUA SUMERGIBLES | B86: B014L | C86: BOMBA SUMERGIBLE TIPO LAPIZ DE 1/2HP 110V MARCA ROCCIA | D86: =IF(MOD(F86, 5) <= 2.5, FLOOR(F86, 5), CEILING(F86, 5)) -> 165 | E86: =IF(MOD(G86, 5) <= 2.5, FLOOR(G86, 5), CEILING(G86, 5)) -> 250 | F86: =IFERROR((VLOOKUP(B86, Roccia!$B$2:$D997, 3, FALSE)*(1+Datos!$E$1)), "Revisar") -> 166.985 | G86: =IFERROR(F86*Datos!$B$3, "Revisar") -> 250.4775 | H86: =IFERROR(G86*Datos!$B$1, "Revisar") -> 144662.3 | I86: =IFERROR((VLOOKUP(B86, Roccia!$B$2:$D997, 3, FALSE) /(1-Datos!$E$1)), "Revisar") -> 183.5 | J86: =IFERROR(I86*Datos!$B$3, "Revisar") -> 275.25 | K86: =IFERROR(J86-G86, "Revisar") -> 24.7725
A87: BOMBAS DE AGUA SUMERGIBLES | B87: B015L | C87: BOMBA SUMERGIBLE TIPO LAPIZ DE 1/2HP 220V MARCA ROCCIA | D87: =IF(MOD(F87, 5) <= 2.5, FLOOR(F87, 5), CEILING(F87, 5)) -> 165 | E87: =IF(MOD(G87, 5) <= 2.5, FLOOR(G87, 5), CEILING(G87, 5)) -> 250 | F87: =IFERROR((VLOOKUP(B87, Roccia!$B$2:$D997, 3, FALSE)*(1+Datos!$E$1)), "Revisar") -> 165.321 | G87: =IFERROR(F87*Datos!$B$3, "Revisar") -> 247.9815 | H87: =IFERROR(G87*Datos!$B$1, "Revisar") -> 143220.75 | I87: =IFERROR((VLOOKUP(B87, Roccia!$B$2:$D997, 3, FALSE) /(1-Datos!$E$1)), "Revisar") -> 181.67143 | J87: =IFERROR(I87*Datos!$B$3, "Revisar") -> 272.50714 | K87: =IFERROR(J87-G87, "Revisar") -> 24.525643
A88: BOMBAS DE AGUA SUMERGIBLES | B88: B016L | C88: BOMBA SUMERGIBLE TIPO LAPIZ DE 3/4HP 220V MARCA ROCCIA | D88: =IF(MOD(F88, 5) <= 2.5, FLOOR(F88, 5), CEILING(F88, 5)) -> 180 | E88: =IF(MOD(G88, 5) <= 2.5, FLOOR(G88, 5), CEILING(G88, 5)) -> 270 | F88: =IFERROR((VLOOKUP(B88, Roccia!$B$2:$D997, 3, FALSE)*(1+Datos!$E$1)), "Revisar") -> 180.648 | G88: =IFERROR(F88*Datos!$B$3, "Revisar") -> 270.972 | H88: =IFERROR(G88*Datos!$B$1, "Revisar") -> 156498.82 | I88: =IFERROR((VLOOKUP(B88, Roccia!$B$2:$D997, 3, FALSE) /(1-Datos!$E$1)), "Revisar") -> 198.51429 | J88: =IFERROR(I88*Datos!$B$3, "Revisar") -> 297.77143 | K88: =IFERROR(J88-G88, "Revisar") -> 26.799429
A89: COCINAS Y RELACIONADOS | B89: C002 | C89: COCINA BLANCA 2 H CARACOL | D89: =IF(MOD(F89, 5) <= 2.5, FLOOR(F89, 5), CEILING(F89, 5)) -> 10 | E89: =IF(MOD(G89, 5) <= 2.5, FLOOR(G89, 5), CEILING(G89, 5)) -> 15 | F89: =IFERROR((VLOOKUP(B89, Roccia!$B$2:$D997, 3, FALSE)*(1+Datos!$E$1)), "Revisar") -> 10.4 | G89: =IFERROR(F89*Datos!$B$3, "Revisar") -> 15.6 | H89: =IFERROR(G89*Datos!$B$1, "Revisar") -> 9009.7192 | I89: =IFERROR((VLOOKUP(B89, Roccia!$B$2:$D997, 3, FALSE) /(1-Datos!$E$1)), "Revisar") -> 11.428571 | J89: =IFERROR(I89*Datos!$B$3, "Revisar") -> 17.142857 | K89: =IFERROR(J89-G89, "Revisar") -> 1.5428571
A90: COCINAS Y RELACIONADOS | B90: C003 | C90: COCINA CROMADA 2H CARACOL | D90: =IF(MOD(F90, 5) <= 2.5, FLOOR(F90, 5), CEILING(F90, 5)) -> 20 | E90: =IF(MOD(G90, 5) <= 2.5, FLOOR(G90, 5), CEILING(G90, 5)) -> 30 | F90: =IFERROR((VLOOKUP(B90, Roccia!$B$2:$D997, 3, FALSE)*(1+Datos!$E$1)), "Revisar") -> 18.85 | G90: =IFERROR(F90*Datos!$B$3, "Revisar") -> 28.275 | H90: =IFERROR(G90*Datos!$B$1, "Revisar") -> 16330.116 | I90: =IFERROR((VLOOKUP(B90, Roccia!$B$2:$D997, 3, FALSE) /(1-Datos!$E$1)), "Revisar") -> 20.714286 | J90: =IFERROR(I90*Datos!$B$3, "Revisar") -> 31.071429 | K90: =IFERROR(J90-G90, "Revisar") -> 2.7964286
A91: COCINAS Y RELACIONADOS | B91: C010 | C91: COCINA INFRARROJA | D91: =IF(MOD(F91, 5) <= 2.5, FLOOR(F91, 5), CEILING(F91, 5)) -> 40 | E91: =IF(MOD(G91, 5) <= 2.5, FLOOR(G91, 5), CEILING(G91, 5)) -> 60 | F91: =IFERROR((VLOOKUP(B91, Roccia!$B$2:$D997, 3, FALSE)*(1+Datos!$E$1)), "Revisar") -> 41.561 | G91: =IFERROR(F91*Datos!$B$3, "Revisar") -> 62.3415 | H91: =IFERROR(G91*Datos!$B$1, "Revisar") -> 36005.09 | I91: =IFERROR((VLOOKUP(B91, Roccia!$B$2:$D997, 3, FALSE) /(1-Datos!$E$1)), "Revisar") -> 45.671429 | J91: =IFERROR(I91*Datos!$B$3, "Revisar") -> 68.507143 | K91: =IFERROR(J91-G91, "Revisar") -> 6.1656429
A92: COCINAS Y RELACIONADOS | B92: C011 | C92: OLLA DE PRESION ELECTRICA | D92: =IF(MOD(F92, 5) <= 2.5, FLOOR(F92, 5), CEILING(F92, 5)) -> 85 | E92: =IF(MOD(G92, 5) <= 2.5, FLOOR(G92, 5), CEILING(G92, 5)) -> 125 | F92: =IFERROR((VLOOKUP(B92, Roccia!$B$2:$D997, 3, FALSE)*(1+Datos!$E$1)), "Revisar") -> 84.721 | G92: =IFERROR(F92*Datos!$B$3, "Revisar") -> 127.0815 | H92: =IFERROR(G92*Datos!$B$1, "Revisar") -> 73395.425 | I92: =IFERROR((VLOOKUP(B92, Roccia!$B$2:$D997, 3, FALSE) /(1-Datos!$E$1)), "Revisar") -> 93.1 | J92: =IFERROR(I92*Datos!$B$3, "Revisar") -> 139.65 | K92: =IFERROR(J92-G92, "Revisar") -> 12.5685
A93: COCINAS Y RELACIONADOS | B93: C012 | C93: COCINA INFRARROJO 110V 2 HORNILLAS 2 EN 1 ROCCIA | D93: =IF(MOD(F93, 5) <= 2.5, FLOOR(F93, 5), CEILING(F93, 5)) -> 155 | E93: =IF(MOD(G93, 5) <= 2.5, FLOOR(G93, 5), CEILING(G93, 5)) -> 235 | F93: =IFERROR((VLOOKUP(B93, Roccia!$B$2:$D997, 3, FALSE)*(1+Datos!$E$1)), "Revisar") -> 155.142 | G93: =IFERROR(F93*Datos!$B$3, "Revisar") -> 232.713 | H93: =IFERROR(G93*Datos!$B$1, "Revisar") -> 134402.49 | I93: =IFERROR((VLOOKUP(B93, Roccia!$B$2:$D997, 3, FALSE) /(1-Datos!$E$1)), "Revisar") -> 170.48571 | J93: =IFERROR(I93*Datos!$B$3, "Revisar") -> 255.72857 | K93: =IFERROR(J93-G93, "Revisar") -> 23.015571
A94: COCINAS Y RELACIONADOS | B94: C013 | C94: COCINA INFRARROJO 220V 2 HORNILLAS 2 EN 1 ROCCIA | D94: =IF(MOD(F94, 5) <= 2.5, FLOOR(F94, 5), CEILING(F94, 5)) -> 140 | E94: =IF(MOD(G94, 5) <= 2.5, FLOOR(G94, 5), CEILING(G94, 5)) -> 210 | F94: =IFERROR((VLOOKUP(B94, Roccia!$B$2:$D997, 3, FALSE)*(1+Datos!$E$1)), "Revisar") -> 140.764 | G94: =IFERROR(F94*Datos!$B$3, "Revisar") -> 211.146 | H94: =IFERROR(G94*Datos!$B$1, "Revisar") -> 121946.55 | I94: =IFERROR((VLOOKUP(B94, Roccia!$B$2:$D997, 3, FALSE) /(1-Datos!$E$1)), "Revisar") -> 154.68571 | J94: =IFERROR(I94*Datos!$B$3, "Revisar") -> 232.02857 | K94: =IFERROR(J94-G94, "Revisar") -> 20.882571
A95: COCINAS Y RELACIONADOS | B95: C014 | C95: COCINA DE INDUCCIÓN 110V 2 HORNILLAS 2 EN 1 ROCCIA | D95: =IF(MOD(F95, 5) <= 2.5, FLOOR(F95, 5), CEILING(F95, 5)) -> 165 | E95: =IF(MOD(G95, 5) <= 2.5, FLOOR(G95, 5), CEILING(G95, 5)) -> 245 | F95: =IFERROR((VLOOKUP(B95, Roccia!$B$2:$D997, 3, FALSE)*(1+Datos!$E$1)), "Revisar") -> 164.385 | G95: =IFERROR(F95*Datos!$B$3, "Revisar") -> 246.5775 | H95: =IFERROR(G95*Datos!$B$1, "Revisar") -> 142409.87 | I95: =IFERROR((VLOOKUP(B95, Roccia!$B$2:$D997, 3, FALSE) /(1-Datos!$E$1)), "Revisar") -> 180.64286 | J95: =IFERROR(I95*Datos!$B$3, "Revisar") -> 270.96429 | K95: =IFERROR(J95-G95, "Revisar") -> 24.386786
A96: COCINAS Y RELACIONADOS | B96: C015 | C96: COCINA DE INDUCCIÓN 220V 2 HORNILLAS 2 EN 1 ROCCIA | D96: =IF(MOD(F96, 5) <= 2.5, FLOOR(F96, 5), CEILING(F96, 5)) -> 145 | E96: =IF(MOD(G96, 5) <= 2.5, FLOOR(G96, 5), CEILING(G96, 5)) -> 220 | F96: =IFERROR((VLOOKUP(B96, Roccia!$B$2:$D997, 3, FALSE)*(1+Datos!$E$1)), "Revisar") -> 145.795 | G96: =IFERROR(F96*Datos!$B$3, "Revisar") -> 218.6925 | H96: =IFERROR(G96*Datos!$B$1, "Revisar") -> 126305 | I96: =IFERROR((VLOOKUP(B96, Roccia!$B$2:$D997, 3, FALSE) /(1-Datos!$E$1)), "Revisar") -> 160.21429 | J96: =IFERROR(I96*Datos!$B$3, "Revisar") -> 240.32143 | K96: =IFERROR(J96-G96, "Revisar") -> 21.628929
A97: COCINAS Y RELACIONADOS | B97: C016 | C97: OLLA DE PRESION ELECTRICA SMART TÁCTIL MARCA ROCCIA | D97: =IF(MOD(F97, 5) <= 2.5, FLOOR(F97, 5), CEILING(F97, 5)) -> 95 | E97: =IF(MOD(G97, 5) <= 2.5, FLOOR(G97, 5), CEILING(G97, 5)) -> 145 | F97: =IFERROR((VLOOKUP(B97, Roccia!$B$2:$D997, 3, FALSE)*(1+Datos!$E$1)), "Revisar") -> 96.304 | G97: =IFERROR(F97*Datos!$B$3, "Revisar") -> 144.456 | H97: =IFERROR(G97*Datos!$B$1, "Revisar") -> 83429.999 | I97: =IFERROR((VLOOKUP(B97, Roccia!$B$2:$D997, 3, FALSE) /(1-Datos!$E$1)), "Revisar") -> 105.82857 | J97: =IFERROR(I97*Datos!$B$3, "Revisar") -> 158.74286 | K97: =IFERROR(J97-G97, "Revisar") -> 14.286857
A98: COCINAS Y RELACIONADOS | B98: C017 | C98: COCINA VITROCERAMICA A GAS 2 QUEMADORES ALTA GAMA JZB-G206b | D98: =IF(MOD(F98, 5) <= 2.5, FLOOR(F98, 5), CEILING(F98, 5)) -> 100 | E98: =IF(MOD(G98, 5) <= 2.5, FLOOR(G98, 5), CEILING(G98, 5)) -> 150 | F98: =IFERROR((VLOOKUP(B98, Roccia!$B$2:$D997, 3, FALSE)*(1+Datos!$E$1)), "Revisar") -> 100.62 | G98: =IFERROR(F98*Datos!$B$3, "Revisar") -> 150.93 | H98: =IFERROR(G98*Datos!$B$1, "Revisar") -> 87169.033 | I98: =IFERROR((VLOOKUP(B98, Roccia!$B$2:$D997, 3, FALSE) /(1-Datos!$E$1)), "Revisar") -> 110.57143 | J98: =IFERROR(I98*Datos!$B$3, "Revisar") -> 165.85714 | K98: =IFERROR(J98-G98, "Revisar") -> 14.927143
A99: COCINAS Y RELACIONADOS | B99: C018 | C99: COCINA VITROCERAMICA A GAS 3 QUEMADORES JZ-G307 | D99: =IF(MOD(F99, 5) <= 2.5, FLOOR(F99, 5), CEILING(F99, 5)) -> 55 | E99: =IF(MOD(G99, 5) <= 2.5, FLOOR(G99, 5), CEILING(G99, 5)) -> 85 | F99: =IFERROR((VLOOKUP(B99, Roccia!$B$2:$D997, 3, FALSE)*(1+Datos!$E$1)), "Revisar") -> 55.601 | G99: =IFERROR(F99*Datos!$B$3, "Revisar") -> 83.4015 | H99: =IFERROR(G99*Datos!$B$1, "Revisar") -> 48168.211 | I99: =IFERROR((VLOOKUP(B99, Roccia!$B$2:$D997, 3, FALSE) /(1-Datos!$E$1)), "Revisar") -> 61.1 | J99: =IFERROR(I99*Datos!$B$3, "Revisar") -> 91.65 | K99: =IFERROR(J99-G99, "Revisar") -> 8.2485
A100: FILTROS PARA PISCINA | B100: B025F | C100: FILTRO DE PISCINA DE 24" MARCA ROCCIA | D100: =IF(MOD(F100, 5) <= 2.5, FLOOR(F100, 5), CEILING(F100, 5)) -> 475 | E100: =IF(MOD(G100, 5) <= 2.5, FLOOR(G100, 5), CEILING(G100, 5)) -> 715 | F100: =IFERROR((VLOOKUP(B100, Roccia!$B$2:$D997, 3, FALSE)*(1+Datos!$E$1)), "Revisar") -> 476.775 | G100: =IFERROR(F100*Datos!$B$3, "Revisar") -> 715.1625 | H100: =IFERROR(G100*Datos!$B$1, "Revisar") -> 413039.31 | I100: =IFERROR((VLOOKUP(B100, Roccia!$B$2:$D997, 3, FALSE) /(1-Datos!$E$1)), "Revisar") -> 523.92857 | J100: =IFERROR(I100*Datos!$B$3, "Revisar") -> 785.89286 | K100: =IFERROR(J100-G100, "Revisar") -> 70.730357
...

Sheet G3 Multi - Ajuste
A1: TIPO | B1: CODIGO | C1: PRODUCTO | D1: PRECIO $ G3Multi | E1: PRECIO $ BCV | F1: PRECIO Bs. | G1: UTILIDAD | H1: P. VENTA UTIL. | I1: diff.
A2: {=Roccia!A2:C997} -> ARTÍCULOS DE COCINA | B2: K001 | C2: JUEGO DE OLLAS DE GRANITO ANTIADHERENTE 12 PIEZAS DE LUJO NERO ROCCIA | D2: =IFERROR((VLOOKUP(B2, Roccia!$B$2:$D997, 3, FALSE)*(1+Datos!$E$2)), "Revisar") -> 132.372 | E2: =IFERROR(D2*Datos!$B$3, "Revisar") -> 198.558 | F2: =IFERROR(E2*Datos!$B$1, "Revisar") -> 114676.4 | G2: =IFERROR((VLOOKUP(B2, Roccia!$B$2:$D997, 3, FALSE) /(1-Datos!$E$1)), "Revisar") -> 157.58571 | H2: =IFERROR(G2*Datos!$B$3, "Revisar") -> 236.37857 | I2: =IFERROR(H2-E2, "Revisar") -> 37.820571
A3: ARTÍCULOS DE COCINA | B3: K003 | C3: JUEGO DE SARTENES 3 PIEZAS NERO MARCA ROCCIA | D3: =IFERROR((VLOOKUP(B3, Roccia!$B$2:$D997, 3, FALSE)*(1+Datos!$E$2)), "Revisar") -> 43.368 | E3: =IFERROR(D3*Datos!$B$3, "Revisar") -> 65.052 | F3: =IFERROR(E3*Datos!$B$1, "Revisar") -> 37570.529 | G3: =IFERROR((VLOOKUP(B3, Roccia!$B$2:$D997, 3, FALSE) /(1-Datos!$E$1)), "Revisar") -> 51.628571 | H3: =IFERROR(G3*Datos!$B$3, "Revisar") -> 77.442857 | I3: =IFERROR(H3-E3, "Revisar") -> 12.390857
A4: ARTÍCULOS DE COCINA | B4: K004 | C4: WOK DE 28CM CON TAPA DE CRISTAL MARCA ROCCIA | D4: =IFERROR((VLOOKUP(B4, Roccia!$B$2:$D997, 3, FALSE)*(1+Datos!$E$2)), "Revisar") -> 25.884 | E4: =IFERROR(D4*Datos!$B$3, "Revisar") -> 38.826 | F4: =IFERROR(E4*Datos!$B$1, "Revisar") -> 22423.805 | G4: =IFERROR((VLOOKUP(B4, Roccia!$B$2:$D997, 3, FALSE) /(1-Datos!$E$1)), "Revisar") -> 30.814286 | H4: =IFERROR(G4*Datos!$B$3, "Revisar") -> 46.221429 | I4: =IFERROR(H4-E4, "Revisar") -> 7.3954286
A5: ARTÍCULOS DE COCINA | B5: K005 | C5: JUEGO DE OLLAS GRANITE 14 PIEZAS MARCA ROCCIA | D5: =IFERROR((VLOOKUP(B5, Roccia!$B$2:$D997, 3, FALSE)*(1+Datos!$E$2)), "Revisar") -> 105.06 | E5: =IFERROR(D5*Datos!$B$3, "Revisar") -> 157.59 | F5: =IFERROR(E5*Datos!$B$1, "Revisar") -> 91015.49 | G5: =IFERROR((VLOOKUP(B5, Roccia!$B$2:$D997, 3, FALSE) /(1-Datos!$E$1)), "Revisar") -> 125.07143 | H5: =IFERROR(G5*Datos!$B$3, "Revisar") -> 187.60714 | I5: =IFERROR(H5-E5, "Revisar") -> 30.017143
A6: ARTÍCULOS DE COCINA | B6: K006 | C6: BUDARE 28CM CUADRADO NERO MARCA ROCCIA | D6: =IFERROR((VLOOKUP(B6, Roccia!$B$2:$D997, 3, FALSE)*(1+Datos!$E$2)), "Revisar") -> 13.188 | E6: =IFERROR(D6*Datos!$B$3, "Revisar") -> 19.782 | F6: =IFERROR(E6*Datos!$B$1, "Revisar") -> 11425.017 | G6: =IFERROR((VLOOKUP(B6, Roccia!$B$2:$D997, 3, FALSE) /(1-Datos!$E$1)), "Revisar") -> 15.7 | H6: =IFERROR(G6*Datos!$B$3, "Revisar") -> 23.55 | I6: =IFERROR(H6-E6, "Revisar") -> 3.768
A7: ARTÍCULOS DE COCINA | B7: K007G | C7: JUEGO DE UTENSILIOS DE COCINA 12 PIEZAS SILICONE ANTIRAYA GRIS | D7: =IFERROR((VLOOKUP(B7, Roccia!$B$2:$D997, 3, FALSE)*(1+Datos!$E$2)), "Revisar") -> 13.2 | E7: =IFERROR(D7*Datos!$B$3, "Revisar") -> 19.8 | F7: =IFERROR(E7*Datos!$B$1, "Revisar") -> 11435.413 | G7: =IFERROR((VLOOKUP(B7, Roccia!$B$2:$D997, 3, FALSE) /(1-Datos!$E$1)), "Revisar") -> 15.714286 | H7: =IFERROR(G7*Datos!$B$3, "Revisar") -> 23.571429 | I7: =IFERROR(H7-E7, "Revisar") -> 3.7714286
A8: ARTÍCULOS DE COCINA | B8: K007V | C8: JUEGO DE UTENSILIOS DE COCINA 12 PIEZAS SILICONE ANTIRAYA VERDE | D8: =IFERROR((VLOOKUP(B8, Roccia!$B$2:$D997, 3, FALSE)*(1+Datos!$E$2)), "Revisar") -> 13.2 | E8: =IFERROR(D8*Datos!$B$3, "Revisar") -> 19.8 | F8: =IFERROR(E8*Datos!$B$1, "Revisar") -> 11435.413 | G8: =IFERROR((VLOOKUP(B8, Roccia!$B$2:$D997, 3, FALSE) /(1-Datos!$E$1)), "Revisar") -> 15.714286 | H8: =IFERROR(G8*Datos!$B$3, "Revisar") -> 23.571429 | I8: =IFERROR(H8-E8, "Revisar") -> 3.7714286
A9: ARTÍCULOS DE COCINA | B9: K007N | C9: JUEGO DE UTENSILIOS DE COCINA 12 PIEZAS SILICONE ANTIRAYA NEGRO | D9: =IFERROR((VLOOKUP(B9, Roccia!$B$2:$D997, 3, FALSE)*(1+Datos!$E$2)), "Revisar") -> 13.2 | E9: =IFERROR(D9*Datos!$B$3, "Revisar") -> 19.8 | F9: =IFERROR(E9*Datos!$B$1, "Revisar") -> 11435.413 | G9: =IFERROR((VLOOKUP(B9, Roccia!$B$2:$D997, 3, FALSE) /(1-Datos!$E$1)), "Revisar") -> 15.714286 | H9: =IFERROR(G9*Datos!$B$3, "Revisar") -> 23.571429 | I9: =IFERROR(H9-E9, "Revisar") -> 3.7714286
A10: ARTÍCULOS DE COCINA | B10: K007B | C10: JUEGO DE UTENSILIOS DE COCINA 12 PIEZAS SILICONE ANTIRAYA BEIGE | D10: =IFERROR((VLOOKUP(B10, Roccia!$B$2:$D997, 3, FALSE)*(1+Datos!$E$2)), "Revisar") -> 13.2 | E10: =IFERROR(D10*Datos!$B$3, "Revisar") -> 19.8 | F10: =IFERROR(E10*Datos!$B$1, "Revisar") -> 11435.413 | G10: =IFERROR((VLOOKUP(B10, Roccia!$B$2:$D997, 3, FALSE) /(1-Datos!$E$1)), "Revisar") -> 15.714286 | H10: =IFERROR(G10*Datos!$B$3, "Revisar") -> 23.571429 | I10: =IFERROR(H10-E10, "Revisar") -> 3.7714286
A11: ARTÍCULOS DE COCINA | B11: K008 | C11: JUEGO DE 7 CUCHILLOS DE ALTA GAMA MARCA ROCCIA | D11: =IFERROR((VLOOKUP(B11, Roccia!$B$2:$D997, 3, FALSE)*(1+Datos!$E$2)), "Revisar") -> 37.092 | E11: =IFERROR(D11*Datos!$B$3, "Revisar") -> 55.638 | F11: =IFERROR(E11*Datos!$B$1, "Revisar") -> 32133.51 | G11: =IFERROR((VLOOKUP(B11, Roccia!$B$2:$D997, 3, FALSE) /(1-Datos!$E$1)), "Revisar") -> 44.157143 | H11: =IFERROR(G11*Datos!$B$3, "Revisar") -> 66.235714 | I11: =IFERROR(H11-E11, "Revisar") -> 10.597714
A12: ARTÍCULOS DE COCINA | B12: K009 | C12: JUEGO DE 5 CUCHILLOS DE ACERO INOXIDABLE | D12: =IFERROR((VLOOKUP(B12, Roccia!$B$2:$D997, 3, FALSE)*(1+Datos!$E$2)), "Revisar") -> 18 | E12: =IFERROR(D12*Datos!$B$3, "Revisar") -> 27 | F12: =IFERROR(E12*Datos!$B$1, "Revisar") -> 15593.745 | G12: =IFERROR((VLOOKUP(B12, Roccia!$B$2:$D997, 3, FALSE) /(1-Datos!$E$1)), "Revisar") -> 21.428571 | H12: =IFERROR(G12*Datos!$B$3, "Revisar") -> 32.142857 | I12: =IFERROR(H12-E12, "Revisar") -> 5.1428571
A13: ARTÍCULOS DE COCINA | B13: K010 | C13: SET DE OLLAS DILUSSO 8 PIEZAS DE ACERO INOXIDABLE MARCA ROCCIA | D13: =IFERROR((VLOOKUP(B13, Roccia!$B$2:$D997, 3, FALSE)*(1+Datos!$E$2)), "Revisar") -> 120.924 | E13: =IFERROR(D13*Datos!$B$3, "Revisar") -> 181.386 | F13: =IFERROR(E13*Datos!$B$1, "Revisar") -> 104758.78 | G13: =IFERROR((VLOOKUP(B13, Roccia!$B$2:$D997, 3, FALSE) /(1-Datos!$E$1)), "Revisar") -> 143.95714 | H13: =IFERROR(G13*Datos!$B$3, "Revisar") -> 215.93571 | I13: =IFERROR(H13-E13, "Revisar") -> 34.549714
A14: ARTÍCULOS DE COCINA | B14: K011 | C14: JUEGO DE OLLAS GRANITE GRIS 14 PIEZAS EURO-14SET MARCA ROCCIA | D14: =IFERROR((VLOOKUP(B14, Roccia!$B$2:$D997, 3, FALSE)*(1+Datos!$E$2)), "Revisar") -> 108.684 | E14: =IFERROR(D14*Datos!$B$3, "Revisar") -> 163.026 | F14: =IFERROR(E14*Datos!$B$1, "Revisar") -> 94155.03 | G14: =IFERROR((VLOOKUP(B14, Roccia!$B$2:$D997, 3, FALSE) /(1-Datos!$E$1)), "Revisar") -> 129.38571 | H14: =IFERROR(G14*Datos!$B$3, "Revisar") -> 194.07857 | I14: =IFERROR(H14-E14, "Revisar") -> 31.052571
A15: ARTÍCULOS DE COCINA | B15: K012 | C15: JUEGO DE OLLAS Di'ROCCA NEGRO 10 PIEZAS ALTA GAMA OF25-10PCS | D15: =IFERROR((VLOOKUP(B15, Roccia!$B$2:$D997, 3, FALSE)*(1+Datos!$E$2)), "Revisar") -> 109.92 | E15: =IFERROR(D15*Datos!$B$3, "Revisar") -> 164.88 | F15: =IFERROR(E15*Datos!$B$1, "Revisar") -> 95225.801 | G15: =IFERROR((VLOOKUP(B15, Roccia!$B$2:$D997, 3, FALSE) /(1-Datos!$E$1)), "Revisar") -> 130.85714 | H15: =IFERROR(G15*Datos!$B$3, "Revisar") -> 196.28571 | I15: =IFERROR(H15-E15, "Revisar") -> 31.405714
A16: ARTÍCULOS DE COCINA | B16: K013 | C16: JUEGO DE OLLAS Di'ROCCA BLANCO 10 PIEZAS ALTA GAMA OF26-10PCS | D16: =IFERROR((VLOOKUP(B16, Roccia!$B$2:$D997, 3, FALSE)*(1+Datos!$E$2)), "Revisar") -> 109.92 | E16: =IFERROR(D16*Datos!$B$3, "Revisar") -> 164.88 | F16: =IFERROR(E16*Datos!$B$1, "Revisar") -> 95225.801 | G16: =IFERROR((VLOOKUP(B16, Roccia!$B$2:$D997, 3, FALSE) /(1-Datos!$E$1)), "Revisar") -> 130.85714 | H16: =IFERROR(G16*Datos!$B$3, "Revisar") -> 196.28571 | I16: =IFERROR(H16-E16, "Revisar") -> 31.405714
A17: ARTICULOS PARA PISCINAS | B17: B029L | C17: LAMPARA LED PARA PISCINA 29.2*7CM CON BORDE 12W/12V YC292-A | D17: =IFERROR((VLOOKUP(B17, Roccia!$B$2:$D997, 3, FALSE)*(1+Datos!$E$2)), "Revisar") -> 48.612 | E17: =IFERROR(D17*Datos!$B$3, "Revisar") -> 72.918 | F17: =IFERROR(E17*Datos!$B$1, "Revisar") -> 42113.507 | G17: =IFERROR((VLOOKUP(B17, Roccia!$B$2:$D997, 3, FALSE) /(1-Datos!$E$1)), "Revisar") -> 57.871429 | H17: =IFERROR(G17*Datos!$B$3, "Revisar") -> 86.807143 | I17: =IFERROR(H17-E17, "Revisar") -> 13.889143
A18: ARTICULOS PARA PISCINAS | B18: B030L | C18: LAMPARA LED PARA PISCINA 29.5*7CM BORDE INFINITO 12W/12V YC295-2A | D18: =IFERROR((VLOOKUP(B18, Roccia!$B$2:$D997, 3, FALSE)*(1+Datos!$E$2)), "Revisar") -> 52.404 | E18: =IFERROR(D18*Datos!$B$3, "Revisar") -> 78.606 | F18: =IFERROR(E18*Datos!$B$1, "Revisar") -> 45398.589 | G18: =IFERROR((VLOOKUP(B18, Roccia!$B$2:$D997, 3, FALSE) /(1-Datos!$E$1)), "Revisar") -> 62.385714 | H18: =IFERROR(G18*Datos!$B$3, "Revisar") -> 93.578571 | I18: =IFERROR(H18-E18, "Revisar") -> 14.972571
A19: ARTICULOS PARA PISCINAS | B19: B031L | C19: LAMPARA LED PARA PISCINA 23*4.8CM 12W/12V YC230-2A | D19: =IFERROR((VLOOKUP(B19, Roccia!$B$2:$D997, 3, FALSE)*(1+Datos!$E$2)), "Revisar") -> 48.576 | E19: =IFERROR(D19*Datos!$B$3, "Revisar") -> 72.864 | F19: =IFERROR(E19*Datos!$B$1, "Revisar") -> 42082.319 | G19: =IFERROR((VLOOKUP(B19, Roccia!$B$2:$D997, 3, FALSE) /(1-Datos!$E$1)), "Revisar") -> 57.828571 | H19: =IFERROR(G19*Datos!$B$3, "Revisar") -> 86.742857 | I19: =IFERROR(H19-E19, "Revisar") -> 13.878857
A20: ARTICULOS PARA PISCINAS | B20: B032L | C20: LAMPARA LED PARA PISCINA 23*4.8CM 12W/12V YC230-SW | D20: =IFERROR((VLOOKUP(B20, Roccia!$B$2:$D997, 3, FALSE)*(1+Datos!$E$2)), "Revisar") -> 48.612 | E20: =IFERROR(D20*Datos!$B$3, "Revisar") -> 72.918 | F20: =IFERROR(E20*Datos!$B$1, "Revisar") -> 42113.507 | G20: =IFERROR((VLOOKUP(B20, Roccia!$B$2:$D997, 3, FALSE) /(1-Datos!$E$1)), "Revisar") -> 57.871429 | H20: =IFERROR(G20*Datos!$B$3, "Revisar") -> 86.807143 | I20: =IFERROR(H20-E20, "Revisar") -> 13.889143
A21: ARTICULOS PARA PISCINAS | B21: B033L | C21: LAMPARA LED PARA PISCINA 30*7CM 18W/12V YC300-SW | D21: =IFERROR((VLOOKUP(B21, Roccia!$B$2:$D997, 3, FALSE)*(1+Datos!$E$2)), "Revisar") -> 70.224 | E21: =IFERROR(D21*Datos!$B$3, "Revisar") -> 105.336 | F21: =IFERROR(E21*Datos!$B$1, "Revisar") -> 60836.396 | G21: =IFERROR((VLOOKUP(B21, Roccia!$B$2:$D997, 3, FALSE) /(1-Datos!$E$1)), "Revisar") -> 83.6 | H21: =IFERROR(G21*Datos!$B$3, "Revisar") -> 125.4 | I21: =IFERROR(H21-E21, "Revisar") -> 20.064
A22: ARTICULOS PARA PISCINAS | B22: B034L | C22: ASPIRADORA DE PISCINAS RECARGABLE 2000MAH 40W RPC403 MARCA ROCCIA | D22: =IFERROR((VLOOKUP(B22, Roccia!$B$2:$D997, 3, FALSE)*(1+Datos!$E$2)), "Revisar") -> 107.46 | E22: =IFERROR(D22*Datos!$B$3, "Revisar") -> 161.19 | F22: =IFERROR(E22*Datos!$B$1, "Revisar") -> 93094.656 | G22: =IFERROR((VLOOKUP(B22, Roccia!$B$2:$D997, 3, FALSE) /(1-Datos!$E$1)), "Revisar") -> 127.92857 | H22: =IFERROR(G22*Datos!$B$3, "Revisar") -> 191.89286 | I22: =IFERROR(H22-E22, "Revisar") -> 30.702857
A23: ARTICULOS PARA PISCINAS | B23: B035L | C23: CLORIFICADOR SALINO INTELIGENTE 25g/h PARA PISCINAS LC250A | D23: =IFERROR((VLOOKUP(B23, Roccia!$B$2:$D997, 3, FALSE)*(1+Datos!$E$2)), "Revisar") -> 464.16 | E23: =IFERROR(D23*Datos!$B$3, "Revisar") -> 696.24 | F23: =IFERROR(E23*Datos!$B$1, "Revisar") -> 402110.7 | G23: =IFERROR((VLOOKUP(B23, Roccia!$B$2:$D997, 3, FALSE) /(1-Datos!$E$1)), "Revisar") -> 552.57143 | H23: =IFERROR(G23*Datos!$B$3, "Revisar") -> 828.85714 | I23: =IFERROR(H23-E23, "Revisar") -> 132.61714
A24: ARTICULOS PARA PISCINAS | B24: B036L | C24: CLORIFICADOR SALINO INTELIGENTE 30g/h PARA PISCINAS LC300A | D24: =IFERROR((VLOOKUP(B24, Roccia!$B$2:$D997, 3, FALSE)*(1+Datos!$E$2)), "Revisar") -> 525.396 | E24: =IFERROR(D24*Datos!$B$3, "Revisar") -> 788.094 | F24: =IFERROR(E24*Datos!$B$1, "Revisar") -> 455160.62 | G24: =IFERROR((VLOOKUP(B24, Roccia!$B$2:$D997, 3, FALSE) /(1-Datos!$E$1)), "Revisar") -> 625.47143 | H24: =IFERROR(G24*Datos!$B$3, "Revisar") -> 938.20714 | I24: =IFERROR(H24-E24, "Revisar") -> 150.11314
A25: ARTICULOS PARA PISCINAS | B25: B037L | C25: CLORIFICADOR SALINO INTELIGENTE 40g/h PARA PISCINAS LC400A | D25: =IFERROR((VLOOKUP(B25, Roccia!$B$2:$D997, 3, FALSE)*(1+Datos!$E$2)), "Revisar") -> 671.412 | E25: =IFERROR(D25*Datos!$B$3, "Revisar") -> 1007.118 | F25: =IFERROR(E25*Datos!$B$1, "Revisar") -> 581657.07 | G25: =IFERROR((VLOOKUP(B25, Roccia!$B$2:$D997, 3, FALSE) /(1-Datos!$E$1)), "Revisar") -> 799.3 | H25: =IFERROR(G25*Datos!$B$3, "Revisar") -> 1198.95 | I25: =IFERROR(H25-E25, "Revisar") -> 191.832
A26: ARTICULOS PARA PISCINAS | B26: B038L | C26: CLORIFICADOR SALINO INTELIGENTE 50g/h PARA PISCINAS LC500A | D26: =IFERROR((VLOOKUP(B26, Roccia!$B$2:$D997, 3, FALSE)*(1+Datos!$E$2)), "Revisar") -> 815.088 | E26: =IFERROR(D26*Datos!$B$3, "Revisar") -> 1222.632 | F26: =IFERROR(E26*Datos!$B$1, "Revisar") -> 706126.34 | G26: =IFERROR((VLOOKUP(B26, Roccia!$B$2:$D997, 3, FALSE) /(1-Datos!$E$1)), "Revisar") -> 970.34286 | H26: =IFERROR(G26*Datos!$B$3, "Revisar") -> 1455.5143 | I26: =IFERROR(H26-E26, "Revisar") -> 232.88229
A27: BALANZAS | B27: P001 | C27: BALANZA DE 40 KG | D27: =IFERROR((VLOOKUP(B27, Roccia!$B$2:$D997, 3, FALSE)*(1+Datos!$E$2)), "Revisar") -> 31.2 | E27: =IFERROR(D27*Datos!$B$3, "Revisar") -> 46.8 | F27: =IFERROR(E27*Datos!$B$1, "Revisar") -> 27029.157 | G27: =IFERROR((VLOOKUP(B27, Roccia!$B$2:$D997, 3, FALSE) /(1-Datos!$E$1)), "Revisar") -> 37.142857 | H27: =IFERROR(G27*Datos!$B$3, "Revisar") -> 55.714286 | I27: =IFERROR(H27-E27, "Revisar") -> 8.9142857
A28: BALANZAS | B28: P003 | C28: BALANZA DE 7 KG | D28: =IFERROR((VLOOKUP(B28, Roccia!$B$2:$D997, 3, FALSE)*(1+Datos!$E$2)), "Revisar") -> 4.2 | E28: =IFERROR(D28*Datos!$B$3, "Revisar") -> 6.3 | F28: =IFERROR(E28*Datos!$B$1, "Revisar") -> 3638.5404 | G28: =IFERROR((VLOOKUP(B28, Roccia!$B$2:$D997, 3, FALSE) /(1-Datos!$E$1)), "Revisar") -> 5 | H28: =IFERROR(G28*Datos!$B$3, "Revisar") -> 7.5 | I28: =IFERROR(H28-E28, "Revisar") -> 1.2
A29: BALANZAS | B29: P011 | C29: ROMANA DE 200 KG | D29: =IFERROR((VLOOKUP(B29, Roccia!$B$2:$D997, 3, FALSE)*(1+Datos!$E$2)), "Revisar") -> 50.4 | E29: =IFERROR(D29*Datos!$B$3, "Revisar") -> 75.6 | F29: =IFERROR(E29*Datos!$B$1, "Revisar") -> 43662.485 | G29: =IFERROR((VLOOKUP(B29, Roccia!$B$2:$D997, 3, FALSE) /(1-Datos!$E$1)), "Revisar") -> 60 | H29: =IFERROR(G29*Datos!$B$3, "Revisar") -> 90 | I29: =IFERROR(H29-E29, "Revisar") -> 14.4
A30: BALANZAS | B30: P012 | C30: ROMANA DE 350 KG | D30: =IFERROR((VLOOKUP(B30, Roccia!$B$2:$D997, 3, FALSE)*(1+Datos!$E$2)), "Revisar") -> 72 | E30: =IFERROR(D30*Datos!$B$3, "Revisar") -> 108 | F30: =IFERROR(E30*Datos!$B$1, "Revisar") -> 62374.979 | G30: =IFERROR((VLOOKUP(B30, Roccia!$B$2:$D997, 3, FALSE) /(1-Datos!$E$1)), "Revisar") -> 85.714286 | H30: =IFERROR(G30*Datos!$B$3, "Revisar") -> 128.57143 | I30: =IFERROR(H30-E30, "Revisar") -> 20.571429
A31: BALANZAS | B31: P013 | C31: ROMANA DE 700 KG | D31: =IFERROR((VLOOKUP(B31, Roccia!$B$2:$D997, 3, FALSE)*(1+Datos!$E$2)), "Revisar") -> 120 | E31: =IFERROR(D31*Datos!$B$3, "Revisar") -> 180 | F31: =IFERROR(E31*Datos!$B$1, "Revisar") -> 103958.3 | G31: =IFERROR((VLOOKUP(B31, Roccia!$B$2:$D997, 3, FALSE) /(1-Datos!$E$1)), "Revisar") -> 142.85714 | H31: =IFERROR(G31*Datos!$B$3, "Revisar") -> 214.28571 | I31: =IFERROR(H31-E31, "Revisar") -> 34.285714
A32: BALANZAS | B32: P014 | C32: ROMANA WIFI 300 KG | D32: =IFERROR((VLOOKUP(B32, Roccia!$B$2:$D997, 3, FALSE)*(1+Datos!$E$2)), "Revisar") -> 87.78 | E32: =IFERROR(D32*Datos!$B$3, "Revisar") -> 131.67 | F32: =IFERROR(E32*Datos!$B$1, "Revisar") -> 76045.495 | G32: =IFERROR((VLOOKUP(B32, Roccia!$B$2:$D997, 3, FALSE) /(1-Datos!$E$1)), "Revisar") -> 104.5 | H32: =IFERROR(G32*Datos!$B$3, "Revisar") -> 156.75 | I32: =IFERROR(H32-E32, "Revisar") -> 25.08
A33: BALANZAS | B33: P016 | C33: ROMANA DE 3T 1*1 | D33: =IFERROR((VLOOKUP(B33, Roccia!$B$2:$D997, 3, FALSE)*(1+Datos!$E$2)), "Revisar") -> 448.476 | E33: =IFERROR(D33*Datos!$B$3, "Revisar") -> 672.714 | F33: =IFERROR(E33*Datos!$B$1, "Revisar") -> 388523.35 | G33: =IFERROR((VLOOKUP(B33, Roccia!$B$2:$D997, 3, FALSE) /(1-Datos!$E$1)), "Revisar") -> 533.9 | H33: =IFERROR(G33*Datos!$B$3, "Revisar") -> 800.85 | I33: =IFERROR(H33-E33, "Revisar") -> 128.136
A34: BALANZAS | B34: P017 | C34: ROMANA DE 3T 1,20*1,20 | D34: =IFERROR((VLOOKUP(B34, Roccia!$B$2:$D997, 3, FALSE)*(1+Datos!$E$2)), "Revisar") -> 475.836 | E34: =IFERROR(D34*Datos!$B$3, "Revisar") -> 713.754 | F34: =IFERROR(E34*Datos!$B$1, "Revisar") -> 412225.84 | G34: =IFERROR((VLOOKUP(B34, Roccia!$B$2:$D997, 3, FALSE) /(1-Datos!$E$1)), "Revisar") -> 566.47143 | H34: =IFERROR(G34*Datos!$B$3, "Revisar") -> 849.70714 | I34: =IFERROR(H34-E34, "Revisar") -> 135.95314
A35: BALANZAS | B35: P018 | C35: ROMANA DE 3T 1,50*2 | D35: =IFERROR((VLOOKUP(B35, Roccia!$B$2:$D997, 3, FALSE)*(1+Datos!$E$2)), "Revisar") -> 783.624 | E35: =IFERROR(D35*Datos!$B$3, "Revisar") -> 1175.436 | F35: =IFERROR(E35*Datos!$B$1, "Revisar") -> 678868.48 | G35: =IFERROR((VLOOKUP(B35, Roccia!$B$2:$D997, 3, FALSE) /(1-Datos!$E$1)), "Revisar") -> 932.88571 | H35: =IFERROR(G35*Datos!$B$3, "Revisar") -> 1399.3286 | I35: =IFERROR(H35-E35, "Revisar") -> 223.89257
A36: BALANZAS | B36: P019 | C36: BALANZA DE GANCHO RECARGABLE 50KG GOOD QUALITY YZ-S03 | D36: =IFERROR((VLOOKUP(B36, Roccia!$B$2:$D997, 3, FALSE)*(1+Datos!$E$2)), "Revisar") -> 8.4 | E36: =IFERROR(D36*Datos!$B$3, "Revisar") -> 12.6 | F36: =IFERROR(E36*Datos!$B$1, "Revisar") -> 7277.0809 | G36: =IFERROR((VLOOKUP(B36, Roccia!$B$2:$D997, 3, FALSE) /(1-Datos!$E$1)), "Revisar") -> 10 | H36: =IFERROR(G36*Datos!$B$3, "Revisar") -> 15 | I36: =IFERROR(H36-E36, "Revisar") -> 2.4
A37: BALANZAS | B37: P020 | C37: BALANZA DE COCINA 3KG GOOD QUALITY X1-C3B | D37: =IFERROR((VLOOKUP(B37, Roccia!$B$2:$D997, 3, FALSE)*(1+Datos!$E$2)), "Revisar") -> 17.7 | E37: =IFERROR(D37*Datos!$B$3, "Revisar") -> 26.55 | F37: =IFERROR(E37*Datos!$B$1, "Revisar") -> 15333.849 | G37: =IFERROR((VLOOKUP(B37, Roccia!$B$2:$D997, 3, FALSE) /(1-Datos!$E$1)), "Revisar") -> 21.071429 | H37: =IFERROR(G37*Datos!$B$3, "Revisar") -> 31.607143 | I37: =IFERROR(H37-E37, "Revisar") -> 5.0571429
A38: BALANZAS | B38: P021 | C38: BALANZA DE MOSTRADOR CAP 30KG DE ALTA PRECISION 905 | D38: =IFERROR((VLOOKUP(B38, Roccia!$B$2:$D997, 3, FALSE)*(1+Datos!$E$2)), "Revisar") -> 40.968 | E38: =IFERROR(D38*Datos!$B$3, "Revisar") -> 61.452 | F38: =IFERROR(E38*Datos!$B$1, "Revisar") -> 35491.363 | G38: =IFERROR((VLOOKUP(B38, Roccia!$B$2:$D997, 3, FALSE) /(1-Datos!$E$1)), "Revisar") -> 48.771429 | H38: =IFERROR(G38*Datos!$B$3, "Revisar") -> 73.157143 | I38: =IFERROR(H38-E38, "Revisar") -> 11.705143
A39: BALANZAS | B39: P021S | C39: BALANZA DE MOSTRADOR CAP 30KG DE ALTA PRECISION 905 CON SENCAMER | D39: =IFERROR((VLOOKUP(B39, Roccia!$B$2:$D997, 3, FALSE)*(1+Datos!$E$2)), "Revisar") -> 72 | E39: =IFERROR(D39*Datos!$B$3, "Revisar") -> 108 | F39: =IFERROR(E39*Datos!$B$1, "Revisar") -> 62374.979 | G39: =IFERROR((VLOOKUP(B39, Roccia!$B$2:$D997, 3, FALSE) /(1-Datos!$E$1)), "Revisar") -> 85.714286 | H39: =IFERROR(G39*Datos!$B$3, "Revisar") -> 128.57143 | I39: =IFERROR(H39-E39, "Revisar") -> 20.571429
A40: BALANZAS | B40: P022 | C40: BALANZA DE MOSTRADOR CON SU VISOR CAP 30KG DE ALTA PRECISION 905ARM | D40: =IFERROR((VLOOKUP(B40, Roccia!$B$2:$D997, 3, FALSE)*(1+Datos!$E$2)), "Revisar") -> 54.216 | E40: =IFERROR(D40*Datos!$B$3, "Revisar") -> 81.324 | F40: =IFERROR(E40*Datos!$B$1, "Revisar") -> 46968.359 | G40: =IFERROR((VLOOKUP(B40, Roccia!$B$2:$D997, 3, FALSE) /(1-Datos!$E$1)), "Revisar") -> 64.542857 | H40: =IFERROR(G40*Datos!$B$3, "Revisar") -> 96.814286 | I40: =IFERROR(H40-E40, "Revisar") -> 15.490286
A41: BALANZAS | B41: P023 | C41: ROMANA CAP 200KG DE ALTA PRECISION 616D | D41: =IFERROR((VLOOKUP(B41, Roccia!$B$2:$D997, 3, FALSE)*(1+Datos!$E$2)), "Revisar") -> 83.184 | E41: =IFERROR(D41*Datos!$B$3, "Revisar") -> 124.776 | F41: =IFERROR(E41*Datos!$B$1, "Revisar") -> 72063.892 | G41: =IFERROR((VLOOKUP(B41, Roccia!$B$2:$D997, 3, FALSE) /(1-Datos!$E$1)), "Revisar") -> 99.028571 | H41: =IFERROR(G41*Datos!$B$3, "Revisar") -> 148.54286 | I41: =IFERROR(H41-E41, "Revisar") -> 23.766857
A42: BALANZAS | B42: P024 | C42: ROMANA CAP 300KG DE ALTA PRECISION 617D | D42: =IFERROR((VLOOKUP(B42, Roccia!$B$2:$D997, 3, FALSE)*(1+Datos!$E$2)), "Revisar") -> 113.208 | E42: =IFERROR(D42*Datos!$B$3, "Revisar") -> 169.812 | F42: =IFERROR(E42*Datos!$B$1, "Revisar") -> 98074.258 | G42: =IFERROR((VLOOKUP(B42, Roccia!$B$2:$D997, 3, FALSE) /(1-Datos!$E$1)), "Revisar") -> 134.77143 | H42: =IFERROR(G42*Datos!$B$3, "Revisar") -> 202.15714 | I42: =IFERROR(H42-E42, "Revisar") -> 32.345143
A43: BALANZAS | B43: P025 | C43: ROMANA CAP 400KG DE ALTA PRECISION 618D | D43: =IFERROR((VLOOKUP(B43, Roccia!$B$2:$D997, 3, FALSE)*(1+Datos!$E$2)), "Revisar") -> 143.22 | E43: =IFERROR(D43*Datos!$B$3, "Revisar") -> 214.83 | F43: =IFERROR(E43*Datos!$B$1, "Revisar") -> 124074.23 | G43: =IFERROR((VLOOKUP(B43, Roccia!$B$2:$D997, 3, FALSE) /(1-Datos!$E$1)), "Revisar") -> 170.5 | H43: =IFERROR(G43*Datos!$B$3, "Revisar") -> 255.75 | I43: =IFERROR(H43-E43, "Revisar") -> 40.92
A44: BALANZAS | B44: P026 | C44: ROMANA DE ACERO INOXIDABLE CAP 200KG DE ALTA PRECISION RS-809 | D44: =IFERROR((VLOOKUP(B44, Roccia!$B$2:$D997, 3, FALSE)*(1+Datos!$E$2)), "Revisar") -> 108.288 | E44: =IFERROR(D44*Datos!$B$3, "Revisar") -> 162.432 | F44: =IFERROR(E44*Datos!$B$1, "Revisar") -> 93811.968 | G44: =IFERROR((VLOOKUP(B44, Roccia!$B$2:$D997, 3, FALSE) /(1-Datos!$E$1)), "Revisar") -> 128.91429 | H44: =IFERROR(G44*Datos!$B$3, "Revisar") -> 193.37143 | I44: =IFERROR(H44-E44, "Revisar") -> 30.939429
A45: BALANZAS | B45: P027 | C45: ROMANA DE ACERO INOXIDABLE CAP 300KG DE ALTA PRECISION RS-810 | D45: =IFERROR((VLOOKUP(B45, Roccia!$B$2:$D997, 3, FALSE)*(1+Datos!$E$2)), "Revisar") -> 151.212 | E45: =IFERROR(D45*Datos!$B$3, "Revisar") -> 226.818 | F45: =IFERROR(E45*Datos!$B$1, "Revisar") -> 130997.85 | G45: =IFERROR((VLOOKUP(B45, Roccia!$B$2:$D997, 3, FALSE) /(1-Datos!$E$1)), "Revisar") -> 180.01429 | H45: =IFERROR(G45*Datos!$B$3, "Revisar") -> 270.02143 | I45: =IFERROR(H45-E45, "Revisar") -> 43.203429
A46: BALANZAS | B46: P028 | C46: ROMANA DE ACERO INOXIDABLE CAP 400KG DE ALTA PRECISION RS-811 | D46: =IFERROR((VLOOKUP(B46, Roccia!$B$2:$D997, 3, FALSE)*(1+Datos!$E$2)), "Revisar") -> 194.028 | E46: =IFERROR(D46*Datos!$B$3, "Revisar") -> 291.042 | F46: =IFERROR(E46*Datos!$B$1, "Revisar") -> 168090.17 | G46: =IFERROR((VLOOKUP(B46, Roccia!$B$2:$D997, 3, FALSE) /(1-Datos!$E$1)), "Revisar") -> 230.98571 | H46: =IFERROR(G46*Datos!$B$3, "Revisar") -> 346.47857 | I46: =IFERROR(H46-E46, "Revisar") -> 55.436571
A47: BALANZAS | B47: P029 | C47: BALANZA MOSTRADOR ANTI-INSECTOS MODELO 969S | D47: =IFERROR((VLOOKUP(B47, Roccia!$B$2:$D997, 3, FALSE)*(1+Datos!$E$2)), "Revisar") -> 50.616 | E47: =IFERROR(D47*Datos!$B$3, "Revisar") -> 75.924 | F47: =IFERROR(E47*Datos!$B$1, "Revisar") -> 43849.61 | G47: =IFERROR((VLOOKUP(B47, Roccia!$B$2:$D997, 3, FALSE) /(1-Datos!$E$1)), "Revisar") -> 60.257143 | H47: =IFERROR(G47*Datos!$B$3, "Revisar") -> 90.385714 | I47: =IFERROR(H47-E47, "Revisar") -> 14.461714
A48: BALANZAS | B48: P029S | C48: BALANZA MOSTRADOR ANTI-INSECTOS MODELO 969S CON SENCAMER | D48: =IFERROR((VLOOKUP(B48, Roccia!$B$2:$D997, 3, FALSE)*(1+Datos!$E$2)), "Revisar") -> 80.616 | E48: =IFERROR(D48*Datos!$B$3, "Revisar") -> 120.924 | F48: =IFERROR(E48*Datos!$B$1, "Revisar") -> 69839.185 | G48: =IFERROR((VLOOKUP(B48, Roccia!$B$2:$D997, 3, FALSE) /(1-Datos!$E$1)), "Revisar") -> 95.971429 | H48: =IFERROR(G48*Datos!$B$3, "Revisar") -> 143.95714 | I48: =IFERROR(H48-E48, "Revisar") -> 23.033143
A49: BALANZAS | B49: P030 | C49: BALANZA DE MOSTRADOR 30KG ETIQUETADORA CON SENCAMER ROP-30 ROCCIA | D49: =IFERROR((VLOOKUP(B49, Roccia!$B$2:$D997, 3, FALSE)*(1+Datos!$E$2)), "Revisar") -> 579.468 | E49: =IFERROR(D49*Datos!$B$3, "Revisar") -> 869.202 | F49: =IFERROR(E49*Datos!$B$1, "Revisar") -> 502004.23 | G49: =IFERROR((VLOOKUP(B49, Roccia!$B$2:$D997, 3, FALSE) /(1-Datos!$E$1)), "Revisar") -> 689.84286 | H49: =IFERROR(G49*Datos!$B$3, "Revisar") -> 1034.7643 | I49: =IFERROR(H49-E49, "Revisar") -> 165.56229
A50: BOMBAS DE AGUA | B50: B001 | C50: BOMBA DE AGUA 1/2 HP | D50: =IFERROR((VLOOKUP(B50, Roccia!$B$2:$D997, 3, FALSE)*(1+Datos!$E$2)), "Revisar") -> 30.72 | E50: =IFERROR(D50*Datos!$B$3, "Revisar") -> 46.08 | F50: =IFERROR(E50*Datos!$B$1, "Revisar") -> 26613.324 | G50: =IFERROR((VLOOKUP(B50, Roccia!$B$2:$D997, 3, FALSE) /(1-Datos!$E$1)), "Revisar") -> 36.571429 | H50: =IFERROR(G50*Datos!$B$3, "Revisar") -> 54.857143 | I50: =IFERROR(H50-E50, "Revisar") -> 8.7771429
A51: BOMBAS DE AGUA | B51: B001C | C51: BOMBA DE AGUA DE 1/2HP PERIFÉRICA 110V ALTA GAMA 100% COBRE MARCA ROCCIA | D51: =IFERROR((VLOOKUP(B51, Roccia!$B$2:$D997, 3, FALSE)*(1+Datos!$E$2)), "Revisar") -> 39.54 | E51: =IFERROR(D51*Datos!$B$3, "Revisar") -> 59.31 | F51: =IFERROR(E51*Datos!$B$1, "Revisar") -> 34254.259 | G51: =IFERROR((VLOOKUP(B51, Roccia!$B$2:$D997, 3, FALSE) /(1-Datos!$E$1)), "Revisar") -> 47.071429 | H51: =IFERROR(G51*Datos!$B$3, "Revisar") -> 70.607143 | I51: =IFERROR(H51-E51, "Revisar") -> 11.297143
A52: BOMBAS DE AGUA | B52: B002 | C52: BOMBA DE AGUA 3/4 HP | D52: =IFERROR((VLOOKUP(B52, Roccia!$B$2:$D997, 3, FALSE)*(1+Datos!$E$2)), "Revisar") -> 57.024 | E52: =IFERROR(D52*Datos!$B$3, "Revisar") -> 85.536 | F52: =IFERROR(E52*Datos!$B$1, "Revisar") -> 49400.983 | G52: =IFERROR((VLOOKUP(B52, Roccia!$B$2:$D997, 3, FALSE) /(1-Datos!$E$1)), "Revisar") -> 67.885714 | H52: =IFERROR(G52*Datos!$B$3, "Revisar") -> 101.82857 | I52: =IFERROR(H52-E52, "Revisar") -> 16.292571
A53: BOMBAS DE AGUA | B53: B002C | C53: BOMBA DE AGUA DE 3/4HP PERIFÉRICA 110V ALTA GAMA 100% COBRE MARCA ROCCIA | D53: =IFERROR((VLOOKUP(B53, Roccia!$B$2:$D997, 3, FALSE)*(1+Datos!$E$2)), "Revisar") -> 64.62 | E53: =IFERROR(D53*Datos!$B$3, "Revisar") -> 96.93 | F53: =IFERROR(E53*Datos!$B$1, "Revisar") -> 55981.543 | G53: =IFERROR((VLOOKUP(B53, Roccia!$B$2:$D997, 3, FALSE) /(1-Datos!$E$1)), "Revisar") -> 76.928571 | H53: =IFERROR(G53*Datos!$B$3, "Revisar") -> 115.39286 | I53: =IFERROR(H53-E53, "Revisar") -> 18.462857
A54: BOMBAS DE AGUA | B54: B003 | C54: BOMBA DE AGUA 1 HP | D54: =IFERROR((VLOOKUP(B54, Roccia!$B$2:$D997, 3, FALSE)*(1+Datos!$E$2)), "Revisar") -> 61.728 | E54: =IFERROR(D54*Datos!$B$3, "Revisar") -> 92.592 | F54: =IFERROR(E54*Datos!$B$1, "Revisar") -> 53476.148 | G54: =IFERROR((VLOOKUP(B54, Roccia!$B$2:$D997, 3, FALSE) /(1-Datos!$E$1)), "Revisar") -> 73.485714 | H54: =IFERROR(G54*Datos!$B$3, "Revisar") -> 110.22857 | I54: =IFERROR(H54-E54, "Revisar") -> 17.636571
A55: BOMBAS DE AGUA | B55: B003C | C55: BOMBA DE AGUA DE 1HP PERIFÉRICA 110V ALTA GAMA 100% COBRE MARCA ROCCIA | D55: =IFERROR((VLOOKUP(B55, Roccia!$B$2:$D997, 3, FALSE)*(1+Datos!$E$2)), "Revisar") -> 71.28 | E55: =IFERROR(D55*Datos!$B$3, "Revisar") -> 106.92 | F55: =IFERROR(E55*Datos!$B$1, "Revisar") -> 61751.229 | G55: =IFERROR((VLOOKUP(B55, Roccia!$B$2:$D997, 3, FALSE) /(1-Datos!$E$1)), "Revisar") -> 84.857143 | H55: =IFERROR(G55*Datos!$B$3, "Revisar") -> 127.28571 | I55: =IFERROR(H55-E55, "Revisar") -> 20.365714
A56: BOMBAS DE AGUA | B56: B004 | C56: BOMBA DE AGUA DE 2HP PERIFERICA AUTOCEBANTE TIPO JET 220V JET-200A MARCA ROCCIA | D56: =IFERROR((VLOOKUP(B56, Roccia!$B$2:$D997, 3, FALSE)*(1+Datos!$E$2)), "Revisar") -> 212.88 | E56: =IFERROR(D56*Datos!$B$3, "Revisar") -> 319.32 | F56: =IFERROR(E56*Datos!$B$1, "Revisar") -> 184422.02 | G56: =IFERROR((VLOOKUP(B56, Roccia!$B$2:$D997, 3, FALSE) /(1-Datos!$E$1)), "Revisar") -> 253.42857 | H56: =IFERROR(G56*Datos!$B$3, "Revisar") -> 380.14286 | I56: =IFERROR(H56-E56, "Revisar") -> 60.822857
A57: BOMBAS DE AGUA | B57: B005 | C57: PRESS CONTROL INTELIGENTE | D57: =IFERROR((VLOOKUP(B57, Roccia!$B$2:$D997, 3, FALSE)*(1+Datos!$E$2)), "Revisar") -> 27.12 | E57: =IFERROR(D57*Datos!$B$3, "Revisar") -> 40.68 | F57: =IFERROR(E57*Datos!$B$1, "Revisar") -> 23494.575 | G57: =IFERROR((VLOOKUP(B57, Roccia!$B$2:$D997, 3, FALSE) /(1-Datos!$E$1)), "Revisar") -> 32.285714 | H57: =IFERROR(G57*Datos!$B$3, "Revisar") -> 48.428571 | I57: =IFERROR(H57-E57, "Revisar") -> 7.7485714
A58: BOMBAS DE AGUA | B58: B006 | C58: PURIFICADOR DE AGUA INTELIGENTE OSMOSIS INVERSA 96W 1,58L/M RO700P | D58: =IFERROR((VLOOKUP(B58, Roccia!$B$2:$D997, 3, FALSE)*(1+Datos!$E$2)), "Revisar") -> 341.328 | E58: =IFERROR(D58*Datos!$B$3, "Revisar") -> 511.992 | F58: =IFERROR(E58*Datos!$B$1, "Revisar") -> 295698.98 | G58: =IFERROR((VLOOKUP(B58, Roccia!$B$2:$D997, 3, FALSE) /(1-Datos!$E$1)), "Revisar") -> 406.34286 | H58: =IFERROR(G58*Datos!$B$3, "Revisar") -> 609.51429 | I58: =IFERROR(H58-E58, "Revisar") -> 97.522286
A59: BOMBAS DE AGUA | B59: B007 | C59: REPUESTO FILTRO DE AGUA PCT FILTRO | D59: =IFERROR((VLOOKUP(B59, Roccia!$B$2:$D997, 3, FALSE)*(1+Datos!$E$2)), "Revisar") -> 47.196 | E59: =IFERROR(D59*Datos!$B$3, "Revisar") -> 70.794 | F59: =IFERROR(E59*Datos!$B$1, "Revisar") -> 40886.799 | G59: =IFERROR((VLOOKUP(B59, Roccia!$B$2:$D997, 3, FALSE) /(1-Datos!$E$1)), "Revisar") -> 56.185714 | H59: =IFERROR(G59*Datos!$B$3, "Revisar") -> 84.278571 | I59: =IFERROR(H59-E59, "Revisar") -> 13.484571
A60: BOMBAS DE AGUA | B60: B008 | C60: REPUESTO FILTRO DE AGUA 600G RO MEMBRANA | D60: =IFERROR((VLOOKUP(B60, Roccia!$B$2:$D997, 3, FALSE)*(1+Datos!$E$2)), "Revisar") -> 71.004 | E60: =IFERROR(D60*Datos!$B$3, "Revisar") -> 106.506 | F60: =IFERROR(E60*Datos!$B$1, "Revisar") -> 61512.125 | G60: =IFERROR((VLOOKUP(B60, Roccia!$B$2:$D997, 3, FALSE) /(1-Datos!$E$1)), "Revisar") -> 84.528571 | H60: =IFERROR(G60*Datos!$B$3, "Revisar") -> 126.79286 | I60: =IFERROR(H60-E60, "Revisar") -> 20.286857
A61: BOMBAS DE AGUA CENTRIFUGAS Y PISCINA | B61: B012C | C61: BOMBA DE AGUA CENTRIFUGA DE 1HP HCM158 110V | D61: =IFERROR((VLOOKUP(B61, Roccia!$B$2:$D997, 3, FALSE)*(1+Datos!$E$2)), "Revisar") -> 102.948 | E61: =IFERROR(D61*Datos!$B$3, "Revisar") -> 154.422 | F61: =IFERROR(E61*Datos!$B$1, "Revisar") -> 89185.824 | G61: =IFERROR((VLOOKUP(B61, Roccia!$B$2:$D997, 3, FALSE) /(1-Datos!$E$1)), "Revisar") -> 122.55714 | H61: =IFERROR(G61*Datos!$B$3, "Revisar") -> 183.83571 | I61: =IFERROR(H61-E61, "Revisar") -> 29.413714
A62: BOMBAS DE AGUA CENTRIFUGAS Y PISCINA | B62: B013C | C62: BOMBA DE AGUA CENTRIFUGA DE 1.5HP HCM180 110V | D62: =IFERROR((VLOOKUP(B62, Roccia!$B$2:$D997, 3, FALSE)*(1+Datos!$E$2)), "Revisar") -> 166.872 | E62: =IFERROR(D62*Datos!$B$3, "Revisar") -> 250.308 | F62: =IFERROR(E62*Datos!$B$1, "Revisar") -> 144564.41 | G62: =IFERROR((VLOOKUP(B62, Roccia!$B$2:$D997, 3, FALSE) /(1-Datos!$E$1)), "Revisar") -> 198.65714 | H62: =IFERROR(G62*Datos!$B$3, "Revisar") -> 297.98571 | I62: =IFERROR(H62-E62, "Revisar") -> 47.677714
A63: BOMBAS DE AGUA CENTRIFUGAS Y PISCINA | B63: B014C | C63: BOMBA DE AGUA CENTRIFUGA DE 2HP HCM190 220V | D63: =IFERROR((VLOOKUP(B63, Roccia!$B$2:$D997, 3, FALSE)*(1+Datos!$E$2)), "Revisar") -> 173.556 | E63: =IFERROR(D63*Datos!$B$3, "Revisar") -> 260.334 | F63: =IFERROR(E63*Datos!$B$1, "Revisar") -> 150354.89 | G63: =IFERROR((VLOOKUP(B63, Roccia!$B$2:$D997, 3, FALSE) /(1-Datos!$E$1)), "Revisar") -> 206.61429 | H63: =IFERROR(G63*Datos!$B$3, "Revisar") -> 309.92143 | I63: =IFERROR(H63-E63, "Revisar") -> 49.587429
A64: BOMBAS DE AGUA CENTRIFUGAS Y PISCINA | B64: B015C | C64: BOMBA DE AGUA CENTRIFUGA DE 3HP HCM200 220V | D64: =IFERROR((VLOOKUP(B64, Roccia!$B$2:$D997, 3, FALSE)*(1+Datos!$E$2)), "Revisar") -> 180.396 | E64: =IFERROR(D64*Datos!$B$3, "Revisar") -> 270.594 | F64: =IFERROR(E64*Datos!$B$1, "Revisar") -> 156280.51 | G64: =IFERROR((VLOOKUP(B64, Roccia!$B$2:$D997, 3, FALSE) /(1-Datos!$E$1)), "Revisar") -> 214.75714 | H64: =IFERROR(G64*Datos!$B$3, "Revisar") -> 322.13571 | I64: =IFERROR(H64-E64, "Revisar") -> 51.541714
A65: BOMBAS DE AGUA CENTRIFUGAS Y PISCINA | B65: B016C | C65: BOMBA CENTRIFUGA IMPULSOR TRIFASICA 4KW 5.5HP HST40-160/40 | D65: =IFERROR((VLOOKUP(B65, Roccia!$B$2:$D997, 3, FALSE)*(1+Datos!$E$2)), "Revisar") -> 588.072 | E65: =IFERROR(D65*Datos!$B$3, "Revisar") -> 882.108 | F65: =IFERROR(E65*Datos!$B$1, "Revisar") -> 509458.04 | G65: =IFERROR((VLOOKUP(B65, Roccia!$B$2:$D997, 3, FALSE) /(1-Datos!$E$1)), "Revisar") -> 700.08571 | H65: =IFERROR(G65*Datos!$B$3, "Revisar") -> 1050.1286 | I65: =IFERROR(H65-E65, "Revisar") -> 168.02057
A66: BOMBAS DE AGUA CENTRIFUGAS Y PISCINA | B66: B017C | C66: BOMBA CENTRIFUGA IMPULSOR TRIFASICA 5.5KW 7.5HP HST40-200/55 | D66: =IFERROR((VLOOKUP(B66, Roccia!$B$2:$D997, 3, FALSE)*(1+Datos!$E$2)), "Revisar") -> 746.16 | E66: =IFERROR(D66*Datos!$B$3, "Revisar") -> 1119.24 | F66: =IFERROR(E66*Datos!$B$1, "Revisar") -> 646412.7 | G66: =IFERROR((VLOOKUP(B66, Roccia!$B$2:$D997, 3, FALSE) /(1-Datos!$E$1)), "Revisar") -> 888.28571 | H66: =IFERROR(G66*Datos!$B$3, "Revisar") -> 1332.4286 | I66: =IFERROR(H66-E66, "Revisar") -> 213.18857
A67: BOMBAS DE AGUA CENTRIFUGAS Y PISCINA | B67: B018C | C67: BOMBA CENTRIFUGA IMPULSOR TRIFASICA 7.5KW 10HP HST40-200/75 | D67: =IFERROR((VLOOKUP(B67, Roccia!$B$2:$D997, 3, FALSE)*(1+Datos!$E$2)), "Revisar") -> 782.376 | E67: =IFERROR(D67*Datos!$B$3, "Revisar") -> 1173.564 | F67: =IFERROR(E67*Datos!$B$1, "Revisar") -> 677787.31 | G67: =IFERROR((VLOOKUP(B67, Roccia!$B$2:$D997, 3, FALSE) /(1-Datos!$E$1)), "Revisar") -> 931.4 | H67: =IFERROR(G67*Datos!$B$3, "Revisar") -> 1397.1 | I67: =IFERROR(H67-E67, "Revisar") -> 223.536
A68: BOMBAS DE AGUA CENTRIFUGAS Y PISCINA | B68: B019C | C68: BOMBA CENTRIFUGA IMPULSOR TRIFASICA 15KW 20HP HST40-250/150 | D68: =IFERROR((VLOOKUP(B68, Roccia!$B$2:$D997, 3, FALSE)*(1+Datos!$E$2)), "Revisar") -> 1525.896 | E68: =IFERROR(D68*Datos!$B$3, "Revisar") -> 2288.844 | F68: =IFERROR(E68*Datos!$B$1, "Revisar") -> 1321912.9 | G68: =IFERROR((VLOOKUP(B68, Roccia!$B$2:$D997, 3, FALSE) /(1-Datos!$E$1)), "Revisar") -> 1816.5429 | H68: =IFERROR(G68*Datos!$B$3, "Revisar") -> 2724.8143 | I68: =IFERROR(H68-E68, "Revisar") -> 435.97029
A69: BOMBAS DE AGUA CENTRIFUGAS Y PISCINA | B69: B020C | C69: BOMBA CENTRIFUGA DOBLE IMPULSOR TRIFASICA 5.5KW 7.5HP HST32-250/55D | D69: =IFERROR((VLOOKUP(B69, Roccia!$B$2:$D997, 3, FALSE)*(1+Datos!$E$2)), "Revisar") -> 929.916 | E69: =IFERROR(D69*Datos!$B$3, "Revisar") -> 1394.874 | F69: =IFERROR(E69*Datos!$B$1, "Revisar") -> 805604.04 | G69: =IFERROR((VLOOKUP(B69, Roccia!$B$2:$D997, 3, FALSE) /(1-Datos!$E$1)), "Revisar") -> 1107.0429 | H69: =IFERROR(G69*Datos!$B$3, "Revisar") -> 1660.5643 | I69: =IFERROR(H69-E69, "Revisar") -> 265.69029
A70: BOMBAS DE AGUA CENTRIFUGAS Y PISCINA | B70: B021C | C70: BOMBA CENTRIFUGA DOBLE IMPULSOR TRIFASICA 7.5KW 10HP HST32-250/75D | D70: =IFERROR((VLOOKUP(B70, Roccia!$B$2:$D997, 3, FALSE)*(1+Datos!$E$2)), "Revisar") -> 975.972 | E70: =IFERROR(D70*Datos!$B$3, "Revisar") -> 1463.958 | F70: =IFERROR(E70*Datos!$B$1, "Revisar") -> 845503.23 | G70: =IFERROR((VLOOKUP(B70, Roccia!$B$2:$D997, 3, FALSE) /(1-Datos!$E$1)), "Revisar") -> 1161.8714 | H70: =IFERROR(G70*Datos!$B$3, "Revisar") -> 1742.8071 | I70: =IFERROR(H70-E70, "Revisar") -> 278.84914
A71: BOMBAS DE AGUA CENTRIFUGAS Y PISCINA | B71: B017P | C71: BOMBA DE AGUA DE 3/4HP DE PISCINAS HFC-552 220V MARCA ROCCIA | D71: =IFERROR((VLOOKUP(B71, Roccia!$B$2:$D997, 3, FALSE)*(1+Datos!$E$2)), "Revisar") -> 116.388 | E71: =IFERROR(D71*Datos!$B$3, "Revisar") -> 174.582 | F71: =IFERROR(E71*Datos!$B$1, "Revisar") -> 100829.15 | G71: =IFERROR((VLOOKUP(B71, Roccia!$B$2:$D997, 3, FALSE) /(1-Datos!$E$1)), "Revisar") -> 138.55714 | H71: =IFERROR(G71*Datos!$B$3, "Revisar") -> 207.83571 | I71: =IFERROR(H71-E71, "Revisar") -> 33.253714
A72: BOMBAS DE AGUA CENTRIFUGAS Y PISCINA | B72: B020P | C72: BOMBA DE AGUA PARA PISCINA DE 1.5HP NEW MODEL HFC-1101 220V | D72: =IFERROR((VLOOKUP(B72, Roccia!$B$2:$D997, 3, FALSE)*(1+Datos!$E$2)), "Revisar") -> 156.624 | E72: =IFERROR(D72*Datos!$B$3, "Revisar") -> 234.936 | F72: =IFERROR(E72*Datos!$B$1, "Revisar") -> 135686.37 | G72: =IFERROR((VLOOKUP(B72, Roccia!$B$2:$D997, 3, FALSE) /(1-Datos!$E$1)), "Revisar") -> 186.45714 | H72: =IFERROR(G72*Datos!$B$3, "Revisar") -> 279.68571 | I72: =IFERROR(H72-E72, "Revisar") -> 44.749714
A73: BOMBAS DE AGUA CENTRIFUGAS Y PISCINA | B73: B021P | C73: BOMBA DE AGUA PARA PISCINA DE 2.0HP NEW MODEL HFC-1501 220V | D73: =IFERROR((VLOOKUP(B73, Roccia!$B$2:$D997, 3, FALSE)*(1+Datos!$E$2)), "Revisar") -> 201.732 | E73: =IFERROR(D73*Datos!$B$3, "Revisar") -> 302.598 | F73: =IFERROR(E73*Datos!$B$1, "Revisar") -> 174764.29 | G73: =IFERROR((VLOOKUP(B73, Roccia!$B$2:$D997, 3, FALSE) /(1-Datos!$E$1)), "Revisar") -> 240.15714 | H73: =IFERROR(G73*Datos!$B$3, "Revisar") -> 360.23571 | I73: =IFERROR(H73-E73, "Revisar") -> 57.637714
A74: BOMBAS DE AGUA CENTRIFUGAS Y PISCINA | B74: B022P | C74: BOMBA DE AGUA PARA PISCINA DE 3.0HP NEW MODEL HFC-2201 220V | D74: =IFERROR((VLOOKUP(B74, Roccia!$B$2:$D997, 3, FALSE)*(1+Datos!$E$2)), "Revisar") -> 261.6 | E74: =IFERROR(D74*Datos!$B$3, "Revisar") -> 392.4 | F74: =IFERROR(E74*Datos!$B$1, "Revisar") -> 226629.09 | G74: =IFERROR((VLOOKUP(B74, Roccia!$B$2:$D997, 3, FALSE) /(1-Datos!$E$1)), "Revisar") -> 311.42857 | H74: =IFERROR(G74*Datos!$B$3, "Revisar") -> 467.14286 | I74: =IFERROR(H74-E74, "Revisar") -> 74.742857
A75: BOMBAS DE AGUA CENTRIFUGAS Y PISCINA | B75: B019AI | C75: BOMBA DE AGUA CENTRIFUGA CON IMPULSOR DE ACERO INOXIDABLE 1HP HCT-26S | D75: =IFERROR((VLOOKUP(B75, Roccia!$B$2:$D997, 3, FALSE)*(1+Datos!$E$2)), "Revisar") -> 129.672 | E75: =IFERROR(D75*Datos!$B$3, "Revisar") -> 194.508 | F75: =IFERROR(E75*Datos!$B$1, "Revisar") -> 112337.34 | G75: =IFERROR((VLOOKUP(B75, Roccia!$B$2:$D997, 3, FALSE) /(1-Datos!$E$1)), "Revisar") -> 154.37143 | H75: =IFERROR(G75*Datos!$B$3, "Revisar") -> 231.55714 | I75: =IFERROR(H75-E75, "Revisar") -> 37.049143
A76: BOMBAS DE AGUA CENTRIFUGAS Y PISCINA | B76: B023C | C76: MOTOBOMBA 2¨ A GASOLINA MARCA ROCCIA GOOD QUALITY | D76: =IFERROR((VLOOKUP(B76, Roccia!$B$2:$D997, 3, FALSE)*(1+Datos!$E$2)), "Revisar") -> 225.276 | E76: =IFERROR(D76*Datos!$B$3, "Revisar") -> 337.914 | F76: =IFERROR(E76*Datos!$B$1, "Revisar") -> 195160.91 | G76: =IFERROR((VLOOKUP(B76, Roccia!$B$2:$D997, 3, FALSE) /(1-Datos!$E$1)), "Revisar") -> 268.18571 | H76: =IFERROR(G76*Datos!$B$3, "Revisar") -> 402.27857 | I76: =IFERROR(H76-E76, "Revisar") -> 64.364571
A77: BOMBAS DE AGUA CENTRIFUGAS Y PISCINA | B77: B024C | C77: MOTOBOMBA 3¨ A GASOLINA MARCA ROCCIA GOOD QUALITY | D77: =IFERROR((VLOOKUP(B77, Roccia!$B$2:$D997, 3, FALSE)*(1+Datos!$E$2)), "Revisar") -> 250.788 | E77: =IFERROR(D77*Datos!$B$3, "Revisar") -> 376.182 | F77: =IFERROR(E77*Datos!$B$1, "Revisar") -> 217262.45 | G77: =IFERROR((VLOOKUP(B77, Roccia!$B$2:$D997, 3, FALSE) /(1-Datos!$E$1)), "Revisar") -> 298.55714 | H77: =IFERROR(G77*Datos!$B$3, "Revisar") -> 447.83571 | I77: =IFERROR(H77-E77, "Revisar") -> 71.653714
A78: BOMBAS DE AGUA CENTRIFUGAS Y PISCINA | B78: B001A | C78: BOMBA DE AGUA DE 1HP DE ACHIQUE WQD750-B MARCA ROCCIA | D78: =IFERROR((VLOOKUP(B78, Roccia!$B$2:$D997, 3, FALSE)*(1+Datos!$E$2)), "Revisar") -> 124.44 | E78: =IFERROR(D78*Datos!$B$3, "Revisar") -> 186.66 | F78: =IFERROR(E78*Datos!$B$1, "Revisar") -> 107804.76 | G78: =IFERROR((VLOOKUP(B78, Roccia!$B$2:$D997, 3, FALSE) /(1-Datos!$E$1)), "Revisar") -> 148.14286 | H78: =IFERROR(G78*Datos!$B$3, "Revisar") -> 222.21429 | I78: =IFERROR(H78-E78, "Revisar") -> 35.554286
A79: BOMBAS DE AGUA SUMERGIBLES | B79: B006S | C79: BOMBA DE AGUA SUMERGIBLE DE 1/2HP 3SE2/9 110V | D79: =IFERROR((VLOOKUP(B79, Roccia!$B$2:$D997, 3, FALSE)*(1+Datos!$E$2)), "Revisar") -> 143.268 | E79: =IFERROR(D79*Datos!$B$3, "Revisar") -> 214.902 | F79: =IFERROR(E79*Datos!$B$1, "Revisar") -> 124115.81 | G79: =IFERROR((VLOOKUP(B79, Roccia!$B$2:$D997, 3, FALSE) /(1-Datos!$E$1)), "Revisar") -> 170.55714 | H79: =IFERROR(G79*Datos!$B$3, "Revisar") -> 255.83571 | I79: =IFERROR(H79-E79, "Revisar") -> 40.933714
A80: BOMBAS DE AGUA SUMERGIBLES | B80: B007S | C80: BOMBA DE AGUA SUMERGIBLE DE 1/2HP 3SE2/9 220V | D80: =IFERROR((VLOOKUP(B80, Roccia!$B$2:$D997, 3, FALSE)*(1+Datos!$E$2)), "Revisar") -> 143.268 | E80: =IFERROR(D80*Datos!$B$3, "Revisar") -> 214.902 | F80: =IFERROR(E80*Datos!$B$1, "Revisar") -> 124115.81 | G80: =IFERROR((VLOOKUP(B80, Roccia!$B$2:$D997, 3, FALSE) /(1-Datos!$E$1)), "Revisar") -> 170.55714 | H80: =IFERROR(G80*Datos!$B$3, "Revisar") -> 255.83571 | I80: =IFERROR(H80-E80, "Revisar") -> 40.933714
A81: BOMBAS DE AGUA SUMERGIBLES | B81: B008S | C81: BOMBA DE AGUA SUMERGIBLE DE 3/4HP 3SE2-13 220V | D81: =IFERROR((VLOOKUP(B81, Roccia!$B$2:$D997, 3, FALSE)*(1+Datos!$E$2)), "Revisar") -> 147.864 | E81: =IFERROR(D81*Datos!$B$3, "Revisar") -> 221.796 | F81: =IFERROR(E81*Datos!$B$1, "Revisar") -> 128097.41 | G81: =IFERROR((VLOOKUP(B81, Roccia!$B$2:$D997, 3, FALSE) /(1-Datos!$E$1)), "Revisar") -> 176.02857 | H81: =IFERROR(G81*Datos!$B$3, "Revisar") -> 264.04286 | I81: =IFERROR(H81-E81, "Revisar") -> 42.246857
A82: BOMBAS DE AGUA SUMERGIBLES | B82: B009S | C82: BOMBA DE AGUA SUMERGIBLE DE 1HP 3SE2-17 220V | D82: =IFERROR((VLOOKUP(B82, Roccia!$B$2:$D997, 3, FALSE)*(1+Datos!$E$2)), "Revisar") -> 169.26 | E82: =IFERROR(D82*Datos!$B$3, "Revisar") -> 253.89 | F82: =IFERROR(E82*Datos!$B$1, "Revisar") -> 146633.18 | G82: =IFERROR((VLOOKUP(B82, Roccia!$B$2:$D997, 3, FALSE) /(1-Datos!$E$1)), "Revisar") -> 201.5 | H82: =IFERROR(G82*Datos!$B$3, "Revisar") -> 302.25 | I82: =IFERROR(H82-E82, "Revisar") -> 48.36
A83: BOMBAS DE AGUA SUMERGIBLES | B83: B010S | C83: BOMBA DE AGUA SUMERGIBLE DE 1.5HP 4SE3-13 220V | D83: =IFERROR((VLOOKUP(B83, Roccia!$B$2:$D997, 3, FALSE)*(1+Datos!$E$2)), "Revisar") -> 216.252 | E83: =IFERROR(D83*Datos!$B$3, "Revisar") -> 324.378 | F83: =IFERROR(E83*Datos!$B$1, "Revisar") -> 187343.25 | G83: =IFERROR((VLOOKUP(B83, Roccia!$B$2:$D997, 3, FALSE) /(1-Datos!$E$1)), "Revisar") -> 257.44286 | H83: =IFERROR(G83*Datos!$B$3, "Revisar") -> 386.16429 | I83: =IFERROR(H83-E83, "Revisar") -> 61.786286
A84: BOMBAS DE AGUA SUMERGIBLES | B84: B011S | C84: BOMBA DE AGUA SUMERGIBLE DE 2HP 4SE3-17 220V | D84: =IFERROR((VLOOKUP(B84, Roccia!$B$2:$D997, 3, FALSE)*(1+Datos!$E$2)), "Revisar") -> 256.56 | E84: =IFERROR(D84*Datos!$B$3, "Revisar") -> 384.84 | F84: =IFERROR(E84*Datos!$B$1, "Revisar") -> 222262.84 | G84: =IFERROR((VLOOKUP(B84, Roccia!$B$2:$D997, 3, FALSE) /(1-Datos!$E$1)), "Revisar") -> 305.42857 | H84: =IFERROR(G84*Datos!$B$3, "Revisar") -> 458.14286 | I84: =IFERROR(H84-E84, "Revisar") -> 73.302857
A85: BOMBAS DE AGUA SUMERGIBLES | B85: B012S | C85: BOMBA DE AGUA DE 5.5HP SUMERGIBLE TRIFÁSICA MARCA ROCCIA | D85: =IFERROR((VLOOKUP(B85, Roccia!$B$2:$D997, 3, FALSE)*(1+Datos!$E$2)), "Revisar") -> 385.512 | E85: =IFERROR(D85*Datos!$B$3, "Revisar") -> 578.268 | F85: =IFERROR(E85*Datos!$B$1, "Revisar") -> 333976.43 | G85: =IFERROR((VLOOKUP(B85, Roccia!$B$2:$D997, 3, FALSE) /(1-Datos!$E$1)), "Revisar") -> 458.94286 | H85: =IFERROR(G85*Datos!$B$3, "Revisar") -> 688.41429 | I85: =IFERROR(H85-E85, "Revisar") -> 110.14629
A86: BOMBAS DE AGUA SUMERGIBLES | B86: B014L | C86: BOMBA SUMERGIBLE TIPO LAPIZ DE 1/2HP 110V MARCA ROCCIA | D86: =IFERROR((VLOOKUP(B86, Roccia!$B$2:$D997, 3, FALSE)*(1+Datos!$E$2)), "Revisar") -> 154.14 | E86: =IFERROR(D86*Datos!$B$3, "Revisar") -> 231.21 | F86: =IFERROR(E86*Datos!$B$1, "Revisar") -> 133534.43 | G86: =IFERROR((VLOOKUP(B86, Roccia!$B$2:$D997, 3, FALSE) /(1-Datos!$E$1)), "Revisar") -> 183.5 | H86: =IFERROR(G86*Datos!$B$3, "Revisar") -> 275.25 | I86: =IFERROR(H86-E86, "Revisar") -> 44.04
A87: BOMBAS DE AGUA SUMERGIBLES | B87: B015L | C87: BOMBA SUMERGIBLE TIPO LAPIZ DE 1/2HP 220V MARCA ROCCIA | D87: =IFERROR((VLOOKUP(B87, Roccia!$B$2:$D997, 3, FALSE)*(1+Datos!$E$2)), "Revisar") -> 152.604 | E87: =IFERROR(D87*Datos!$B$3, "Revisar") -> 228.906 | F87: =IFERROR(E87*Datos!$B$1, "Revisar") -> 132203.77 | G87: =IFERROR((VLOOKUP(B87, Roccia!$B$2:$D997, 3, FALSE) /(1-Datos!$E$1)), "Revisar") -> 181.67143 | H87: =IFERROR(G87*Datos!$B$3, "Revisar") -> 272.50714 | I87: =IFERROR(H87-E87, "Revisar") -> 43.601143
A88: BOMBAS DE AGUA SUMERGIBLES | B88: B016L | C88: BOMBA SUMERGIBLE TIPO LAPIZ DE 3/4HP 220V MARCA ROCCIA | D88: =IFERROR((VLOOKUP(B88, Roccia!$B$2:$D997, 3, FALSE)*(1+Datos!$E$2)), "Revisar") -> 166.752 | E88: =IFERROR(D88*Datos!$B$3, "Revisar") -> 250.128 | F88: =IFERROR(E88*Datos!$B$1, "Revisar") -> 144460.45 | G88: =IFERROR((VLOOKUP(B88, Roccia!$B$2:$D997, 3, FALSE) /(1-Datos!$E$1)), "Revisar") -> 198.51429 | H88: =IFERROR(G88*Datos!$B$3, "Revisar") -> 297.77143 | I88: =IFERROR(H88-E88, "Revisar") -> 47.643429
A89: COCINAS Y RELACIONADOS | B89: C002 | C89: COCINA BLANCA 2 H CARACOL | D89: =IFERROR((VLOOKUP(B89, Roccia!$B$2:$D997, 3, FALSE)*(1+Datos!$E$2)), "Revisar") -> 9.6 | E89: =IFERROR(D89*Datos!$B$3, "Revisar") -> 14.4 | F89: =IFERROR(E89*Datos!$B$1, "Revisar") -> 8316.6638 | G89: =IFERROR((VLOOKUP(B89, Roccia!$B$2:$D997, 3, FALSE) /(1-Datos!$E$1)), "Revisar") -> 11.428571 | H89: =IFERROR(G89*Datos!$B$3, "Revisar") -> 17.142857 | I89: =IFERROR(H89-E89, "Revisar") -> 2.7428571
A90: COCINAS Y RELACIONADOS | B90: C003 | C90: COCINA CROMADA 2H CARACOL | D90: =IFERROR((VLOOKUP(B90, Roccia!$B$2:$D997, 3, FALSE)*(1+Datos!$E$2)), "Revisar") -> 17.4 | E90: =IFERROR(D90*Datos!$B$3, "Revisar") -> 26.1 | F90: =IFERROR(E90*Datos!$B$1, "Revisar") -> 15073.953 | G90: =IFERROR((VLOOKUP(B90, Roccia!$B$2:$D997, 3, FALSE) /(1-Datos!$E$1)), "Revisar") -> 20.714286 | H90: =IFERROR(G90*Datos!$B$3, "Revisar") -> 31.071429 | I90: =IFERROR(H90-E90, "Revisar") -> 4.9714286
A91: COCINAS Y RELACIONADOS | B91: C010 | C91: COCINA INFRARROJA | D91: =IFERROR((VLOOKUP(B91, Roccia!$B$2:$D997, 3, FALSE)*(1+Datos!$E$2)), "Revisar") -> 38.364 | E91: =IFERROR(D91*Datos!$B$3, "Revisar") -> 57.546 | F91: =IFERROR(E91*Datos!$B$1, "Revisar") -> 33235.468 | G91: =IFERROR((VLOOKUP(B91, Roccia!$B$2:$D997, 3, FALSE) /(1-Datos!$E$1)), "Revisar") -> 45.671429 | H91: =IFERROR(G91*Datos!$B$3, "Revisar") -> 68.507143 | I91: =IFERROR(H91-E91, "Revisar") -> 10.961143
A92: COCINAS Y RELACIONADOS | B92: C011 | C92: OLLA DE PRESION ELECTRICA | D92: =IFERROR((VLOOKUP(B92, Roccia!$B$2:$D997, 3, FALSE)*(1+Datos!$E$2)), "Revisar") -> 78.204 | E92: =IFERROR(D92*Datos!$B$3, "Revisar") -> 117.306 | F92: =IFERROR(E92*Datos!$B$1, "Revisar") -> 67749.623 | G92: =IFERROR((VLOOKUP(B92, Roccia!$B$2:$D997, 3, FALSE) /(1-Datos!$E$1)), "Revisar") -> 93.1 | H92: =IFERROR(G92*Datos!$B$3, "Revisar") -> 139.65 | I92: =IFERROR(H92-E92, "Revisar") -> 22.344
A93: COCINAS Y RELACIONADOS | B93: C012 | C93: COCINA INFRARROJO 110V 2 HORNILLAS 2 EN 1 ROCCIA | D93: =IFERROR((VLOOKUP(B93, Roccia!$B$2:$D997, 3, FALSE)*(1+Datos!$E$2)), "Revisar") -> 143.208 | E93: =IFERROR(D93*Datos!$B$3, "Revisar") -> 214.812 | F93: =IFERROR(E93*Datos!$B$1, "Revisar") -> 124063.83 | G93: =IFERROR((VLOOKUP(B93, Roccia!$B$2:$D997, 3, FALSE) /(1-Datos!$E$1)), "Revisar") -> 170.48571 | H93: =IFERROR(G93*Datos!$B$3, "Revisar") -> 255.72857 | I93: =IFERROR(H93-E93, "Revisar") -> 40.916571
A94: COCINAS Y RELACIONADOS | B94: C013 | C94: COCINA INFRARROJO 220V 2 HORNILLAS 2 EN 1 ROCCIA | D94: =IFERROR((VLOOKUP(B94, Roccia!$B$2:$D997, 3, FALSE)*(1+Datos!$E$2)), "Revisar") -> 129.936 | E94: =IFERROR(D94*Datos!$B$3, "Revisar") -> 194.904 | F94: =IFERROR(E94*Datos!$B$1, "Revisar") -> 112566.05 | G94: =IFERROR((VLOOKUP(B94, Roccia!$B$2:$D997, 3, FALSE) /(1-Datos!$E$1)), "Revisar") -> 154.68571 | H94: =IFERROR(G94*Datos!$B$3, "Revisar") -> 232.02857 | I94: =IFERROR(H94-E94, "Revisar") -> 37.124571
A95: COCINAS Y RELACIONADOS | B95: C014 | C95: COCINA DE INDUCCIÓN 110V 2 HORNILLAS 2 EN 1 ROCCIA | D95: =IFERROR((VLOOKUP(B95, Roccia!$B$2:$D997, 3, FALSE)*(1+Datos!$E$2)), "Revisar") -> 151.74 | E95: =IFERROR(D95*Datos!$B$3, "Revisar") -> 227.61 | F95: =IFERROR(E95*Datos!$B$1, "Revisar") -> 131455.27 | G95: =IFERROR((VLOOKUP(B95, Roccia!$B$2:$D997, 3, FALSE) /(1-Datos!$E$1)), "Revisar") -> 180.64286 | H95: =IFERROR(G95*Datos!$B$3, "Revisar") -> 270.96429 | I95: =IFERROR(H95-E95, "Revisar") -> 43.354286
A96: COCINAS Y RELACIONADOS | B96: C015 | C96: COCINA DE INDUCCIÓN 220V 2 HORNILLAS 2 EN 1 ROCCIA | D96: =IFERROR((VLOOKUP(B96, Roccia!$B$2:$D997, 3, FALSE)*(1+Datos!$E$2)), "Revisar") -> 134.58 | E96: =IFERROR(D96*Datos!$B$3, "Revisar") -> 201.87 | F96: =IFERROR(E96*Datos!$B$1, "Revisar") -> 116589.23 | G96: =IFERROR((VLOOKUP(B96, Roccia!$B$2:$D997, 3, FALSE) /(1-Datos!$E$1)), "Revisar") -> 160.21429 | H96: =IFERROR(G96*Datos!$B$3, "Revisar") -> 240.32143 | I96: =IFERROR(H96-E96, "Revisar") -> 38.451429
A97: COCINAS Y RELACIONADOS | B97: C016 | C97: OLLA DE PRESION ELECTRICA SMART TÁCTIL MARCA ROCCIA | D97: =IFERROR((VLOOKUP(B97, Roccia!$B$2:$D997, 3, FALSE)*(1+Datos!$E$2)), "Revisar") -> 88.896 | E97: =IFERROR(D97*Datos!$B$3, "Revisar") -> 133.344 | F97: =IFERROR(E97*Datos!$B$1, "Revisar") -> 77012.307 | G97: =IFERROR((VLOOKUP(B97, Roccia!$B$2:$D997, 3, FALSE) /(1-Datos!$E$1)), "Revisar") -> 105.82857 | H97: =IFERROR(G97*Datos!$B$3, "Revisar") -> 158.74286 | I97: =IFERROR(H97-E97, "Revisar") -> 25.398857
A98: COCINAS Y RELACIONADOS | B98: C017 | C98: COCINA VITROCERAMICA A GAS 2 QUEMADORES ALTA GAMA JZB-G206b | D98: =IFERROR((VLOOKUP(B98, Roccia!$B$2:$D997, 3, FALSE)*(1+Datos!$E$2)), "Revisar") -> 92.88 | E98: =IFERROR(D98*Datos!$B$3, "Revisar") -> 139.32 | F98: =IFERROR(E98*Datos!$B$1, "Revisar") -> 80463.723 | G98: =IFERROR((VLOOKUP(B98, Roccia!$B$2:$D997, 3, FALSE) /(1-Datos!$E$1)), "Revisar") -> 110.57143 | H98: =IFERROR(G98*Datos!$B$3, "Revisar") -> 165.85714 | I98: =IFERROR(H98-E98, "Revisar") -> 26.537143
A99: COCINAS Y RELACIONADOS | B99: C018 | C99: COCINA VITROCERAMICA A GAS 3 QUEMADORES JZ-G307 | D99: =IFERROR((VLOOKUP(B99, Roccia!$B$2:$D997, 3, FALSE)*(1+Datos!$E$2)), "Revisar") -> 51.324 | E99: =IFERROR(D99*Datos!$B$3, "Revisar") -> 76.986 | F99: =IFERROR(E99*Datos!$B$1, "Revisar") -> 44462.964 | G99: =IFERROR((VLOOKUP(B99, Roccia!$B$2:$D997, 3, FALSE) /(1-Datos!$E$1)), "Revisar") -> 61.1 | H99: =IFERROR(G99*Datos!$B$3, "Revisar") -> 91.65 | I99: =IFERROR(H99-E99, "Revisar") -> 14.664
A100: FILTROS PARA PISCINA | B100: B025F | C100: FILTRO DE PISCINA DE 24" MARCA ROCCIA | D100: =IFERROR((VLOOKUP(B100, Roccia!$B$2:$D997, 3, FALSE)*(1+Datos!$E$2)), "Revisar") -> 440.1 | E100: =IFERROR(D100*Datos!$B$3, "Revisar") -> 660.15 | F100: =IFERROR(E100*Datos!$B$1, "Revisar") -> 381267.06 | G100: =IFERROR((VLOOKUP(B100, Roccia!$B$2:$D997, 3, FALSE) /(1-Datos!$E$1)), "Revisar") -> 523.92857 | H100: =IFERROR(G100*Datos!$B$3, "Revisar") -> 785.89286 | I100: =IFERROR(H100-E100, "Revisar") -> 125.74286
...

Sheet Datos
A1: BCV | B1: 577.5461 | C1: 46184.481 | D1: Ganancia | E1: 0.3
A2: Binance | B2: 866.31 | D2: Ganancia - Sin Ajuste | E2: 0.2
A3: % Venta | B3: =ROUNDUP(((B2-B1)/B1)+1,2) -> 1.5

Sheet Roccia
A1: TIPO | B1: CODIGO | C1: PRODUCTO | D1: COSTO
A2: ARTÍCULOS DE COCINA | B2: K001 | C2: JUEGO DE OLLAS DE GRANITO ANTIADHERENTE 12 PIEZAS DE LUJO NERO ROCCIA | D2: 110.31
A3: ARTÍCULOS DE COCINA | B3: K003 | C3: JUEGO DE SARTENES 3 PIEZAS NERO MARCA ROCCIA | D3: 36.14
A4: ARTÍCULOS DE COCINA | B4: K004 | C4: WOK DE 28CM CON TAPA DE CRISTAL MARCA ROCCIA | D4: 21.57
A5: ARTÍCULOS DE COCINA | B5: K005 | C5: JUEGO DE OLLAS GRANITE 14 PIEZAS MARCA ROCCIA | D5: 87.55
A6: ARTÍCULOS DE COCINA | B6: K006 | C6: BUDARE 28CM CUADRADO NERO MARCA ROCCIA | D6: 10.99
A7: ARTÍCULOS DE COCINA | B7: K007G | C7: JUEGO DE UTENSILIOS DE COCINA 12 PIEZAS SILICONE ANTIRAYA GRIS | D7: 11
A8: ARTÍCULOS DE COCINA | B8: K007V | C8: JUEGO DE UTENSILIOS DE COCINA 12 PIEZAS SILICONE ANTIRAYA VERDE | D8: 11
A9: ARTÍCULOS DE COCINA | B9: K007N | C9: JUEGO DE UTENSILIOS DE COCINA 12 PIEZAS SILICONE ANTIRAYA NEGRO | D9: 11
A10: ARTÍCULOS DE COCINA | B10: K007B | C10: JUEGO DE UTENSILIOS DE COCINA 12 PIEZAS SILICONE ANTIRAYA BEIGE | D10: 11
A11: ARTÍCULOS DE COCINA | B11: K008 | C11: JUEGO DE 7 CUCHILLOS DE ALTA GAMA MARCA ROCCIA | D11: 30.91
A12: ARTÍCULOS DE COCINA | B12: K009 | C12: JUEGO DE 5 CUCHILLOS DE ACERO INOXIDABLE | D12: 15
A13: ARTÍCULOS DE COCINA | B13: K010 | C13: SET DE OLLAS DILUSSO 8 PIEZAS DE ACERO INOXIDABLE MARCA ROCCIA | D13: 100.77
... A397: VENTILADORES | B397: F027 | C397: VENTILADOR DE PARED 16¨ METAL PLASTICO CON CONTROL MARCA ROCCIA | D397: 23.61

Sheet Pagos
A1: Semana | B1: Fecha | C1: Monto | D1: Corresponde | E1: Referencia
A2: 12/04 al 18/04 | B2: 13/04/2026 | C2: 15000 | D2: 25 | E2: 61032341240
A3: 19/04 al 25/04 | B3: --- | C3: --- | D3: --- | E3: ---
A4: 26/04 al 02/05 | B4: 27/04/2026 | C4: 15000 | D4: 25 | E4: 61175275979
A5: 03/05 al 09/05 | B5: 46178 | C5: 15500 | D5: 25 | E5: 61263587001
A6: 10/05 al 16/05 | B6: 19/05/2026 | C6: 19500 | D6: 30
A7: 17/05 al 23/05 | B7: 26/05/2026 | C7: 21000 | D7: 30
A8: 24/05 al 30/05
A9: 31/05 al 06/06
